{
"meta":{"test_sets":[],"test_metrics":[],"learn_metrics":[{"best_value":"Min","name":"RMSE"}],"launch_mode":"Train","parameters":"","iteration_count":1000,"learn_sets":["learn"],"name":"experiment"},
"iterations":[
{"learn":[91810.86056],"iteration":0,"passed_time":0.185918063,"remaining_time":185.7321449},
{"learn":[88960.89682],"iteration":1,"passed_time":0.2416222384,"remaining_time":120.5694969},
{"learn":[86372.0258],"iteration":2,"passed_time":0.2971582044,"remaining_time":98.75557659},
{"learn":[83777.00493],"iteration":3,"passed_time":0.3564301582,"remaining_time":88.7511094},
{"learn":[81516.13574],"iteration":4,"passed_time":0.4163282072,"remaining_time":82.84931323},
{"learn":[79319.61512],"iteration":5,"passed_time":0.4712421438,"remaining_time":78.06911515},
{"learn":[77129.36833],"iteration":6,"passed_time":0.5293613428,"remaining_time":75.09368763},
{"learn":[74813.12775],"iteration":7,"passed_time":0.5832038677,"remaining_time":72.31727959},
{"learn":[72638.50225],"iteration":8,"passed_time":0.7136253756,"remaining_time":78.57808303},
{"learn":[70550.96891],"iteration":9,"passed_time":0.7708967345,"remaining_time":76.31877672},
{"learn":[68579.10837],"iteration":10,"passed_time":0.8293012667,"remaining_time":74.56172298},
{"learn":[66769.88533],"iteration":11,"passed_time":0.8840873683,"remaining_time":72.78985999},
{"learn":[64921.95696],"iteration":12,"passed_time":0.9440237102,"remaining_time":71.67318477},
{"learn":[63113.89115],"iteration":13,"passed_time":0.9981507922,"remaining_time":70.29833436},
{"learn":[61334.72521],"iteration":14,"passed_time":1.054858058,"remaining_time":69.2690125},
{"learn":[59762.88157],"iteration":15,"passed_time":1.126152359,"remaining_time":69.25837011},
{"learn":[58248.93362],"iteration":16,"passed_time":1.192761202,"remaining_time":68.96966244},
{"learn":[56884.6883],"iteration":17,"passed_time":1.258876576,"remaining_time":68.678711},
{"learn":[55522.75661],"iteration":18,"passed_time":1.316798836,"remaining_time":67.98840307},
{"learn":[54303.51402],"iteration":19,"passed_time":1.370792353,"remaining_time":67.16882528},
{"learn":[53061.40839],"iteration":20,"passed_time":1.423658864,"remaining_time":66.36962038},
{"learn":[51881.02134],"iteration":21,"passed_time":1.481844296,"remaining_time":65.8747146},
{"learn":[50651.25612],"iteration":22,"passed_time":1.54112234,"remaining_time":65.46419677},
{"learn":[49585.27205],"iteration":23,"passed_time":1.599144106,"remaining_time":65.0318603},
{"learn":[48529.17571],"iteration":24,"passed_time":1.659219802,"remaining_time":64.70957228},
{"learn":[47434.42393],"iteration":25,"passed_time":1.715613863,"remaining_time":64.26953471},
{"learn":[46431.24919],"iteration":26,"passed_time":1.768803117,"remaining_time":63.74242344},
{"learn":[45404.46811],"iteration":27,"passed_time":1.822770246,"remaining_time":63.27616711},
{"learn":[44542.09384],"iteration":28,"passed_time":1.884353015,"remaining_time":63.09333715},
{"learn":[43712.1831],"iteration":29,"passed_time":1.94375928,"remaining_time":62.84821671},
{"learn":[42923.9744],"iteration":30,"passed_time":2.004824829,"remaining_time":62.66694386},
{"learn":[42277.64894],"iteration":31,"passed_time":2.063903439,"remaining_time":62.43307902},
{"learn":[41627.9637],"iteration":32,"passed_time":2.121267438,"remaining_time":62.159564},
{"learn":[40919.11735],"iteration":33,"passed_time":2.18456327,"remaining_time":62.0672976},
{"learn":[40359.16202],"iteration":34,"passed_time":2.237858213,"remaining_time":61.70094788},
{"learn":[39740.10144],"iteration":35,"passed_time":2.293164475,"remaining_time":61.40584871},
{"learn":[39034.57379],"iteration":36,"passed_time":2.354530702,"remaining_time":61.28143422},
{"learn":[38465.43872],"iteration":37,"passed_time":2.411601142,"remaining_time":61.05158679},
{"learn":[37965.64056],"iteration":38,"passed_time":2.462850879,"remaining_time":60.68717167},
{"learn":[37408.74802],"iteration":39,"passed_time":2.517051738,"remaining_time":60.40924171},
{"learn":[36851.31268],"iteration":40,"passed_time":2.569993768,"remaining_time":60.11278106},
{"learn":[36391.89218],"iteration":41,"passed_time":2.623727467,"remaining_time":59.84597413},
{"learn":[35957.74596],"iteration":42,"passed_time":2.686322947,"remaining_time":59.78630372},
{"learn":[35482.16206],"iteration":43,"passed_time":2.744896674,"remaining_time":59.63911865},
{"learn":[35146.85375],"iteration":44,"passed_time":2.805104144,"remaining_time":59.5305435},
{"learn":[34755.95587],"iteration":45,"passed_time":2.86309923,"remaining_time":59.37818838},
{"learn":[34418.99469],"iteration":46,"passed_time":2.918202377,"remaining_time":59.17120989},
{"learn":[34106.49709],"iteration":47,"passed_time":2.972282252,"remaining_time":58.95026466},
{"learn":[33778.31018],"iteration":48,"passed_time":3.029508413,"remaining_time":58.79719389},
{"learn":[33484.30499],"iteration":49,"passed_time":3.089809007,"remaining_time":58.70637114},
{"learn":[33131.83115],"iteration":50,"passed_time":3.147815528,"remaining_time":58.57405756},
{"learn":[32881.56567],"iteration":51,"passed_time":3.2067194,"remaining_time":58.46096138},
{"learn":[32576.57781],"iteration":52,"passed_time":3.260438033,"remaining_time":58.2572607},
{"learn":[32349.96485],"iteration":53,"passed_time":3.312141479,"remaining_time":58.02381183},
{"learn":[32041.58719],"iteration":54,"passed_time":3.367378982,"remaining_time":57.85769341},
{"learn":[31798.91711],"iteration":55,"passed_time":3.425810155,"remaining_time":57.74937118},
{"learn":[31563.60175],"iteration":56,"passed_time":3.477843809,"remaining_time":57.53695985},
{"learn":[31310.31564],"iteration":57,"passed_time":3.537818017,"remaining_time":57.45904434},
{"learn":[31126.87934],"iteration":58,"passed_time":3.589810929,"remaining_time":57.2544421},
{"learn":[30901.93993],"iteration":59,"passed_time":3.639907774,"remaining_time":57.0252218},
{"learn":[30747.56225],"iteration":60,"passed_time":3.697032973,"remaining_time":56.91006495},
{"learn":[30543.00753],"iteration":61,"passed_time":3.797546129,"remaining_time":57.45319788},
{"learn":[30345.97215],"iteration":62,"passed_time":3.852542875,"remaining_time":57.29893134},
{"learn":[30121.97874],"iteration":63,"passed_time":3.91115806,"remaining_time":57.20068663},
{"learn":[29919.17719],"iteration":64,"passed_time":3.966452888,"remaining_time":57.05589923},
{"learn":[29731.80227],"iteration":65,"passed_time":4.018359998,"remaining_time":56.86588239},
{"learn":[29545.54611],"iteration":66,"passed_time":4.070433513,"remaining_time":56.68230549},
{"learn":[29371.61712],"iteration":67,"passed_time":4.125675511,"remaining_time":56.54602318},
{"learn":[29201.59114],"iteration":68,"passed_time":4.182701568,"remaining_time":56.43616174},
{"learn":[29079.25106],"iteration":69,"passed_time":4.239328063,"remaining_time":56.32250141},
{"learn":[28964.34324],"iteration":70,"passed_time":4.290992386,"remaining_time":56.14552009},
{"learn":[28796.6541],"iteration":71,"passed_time":4.342342474,"remaining_time":55.96796966},
{"learn":[28582.02376],"iteration":72,"passed_time":4.399056102,"remaining_time":55.86198639},
{"learn":[28465.10437],"iteration":73,"passed_time":4.45297179,"remaining_time":55.72232267},
{"learn":[28329.74399],"iteration":74,"passed_time":4.514632112,"remaining_time":55.68046272},
{"learn":[28208.08489],"iteration":75,"passed_time":4.588337087,"remaining_time":55.78451933},
{"learn":[28130.78864],"iteration":76,"passed_time":4.639991027,"remaining_time":55.6196327},
{"learn":[27922.21274],"iteration":77,"passed_time":4.696544244,"remaining_time":55.51556145},
{"learn":[27801.95888],"iteration":78,"passed_time":4.752286269,"remaining_time":55.40323613},
{"learn":[27721.6443],"iteration":79,"passed_time":4.827068671,"remaining_time":55.51128972},
{"learn":[27580.3034],"iteration":80,"passed_time":4.884887211,"remaining_time":55.42236231},
{"learn":[27468.25262],"iteration":81,"passed_time":4.945361363,"remaining_time":55.36392356},
{"learn":[27411.44098],"iteration":82,"passed_time":4.999396595,"remaining_time":55.23429733},
{"learn":[27319.13374],"iteration":83,"passed_time":5.051445848,"remaining_time":55.08481424},
{"learn":[27205.77807],"iteration":84,"passed_time":5.107126428,"remaining_time":54.9767139},
{"learn":[27074.52349],"iteration":85,"passed_time":5.161746975,"remaining_time":54.85856669},
{"learn":[26972.61684],"iteration":86,"passed_time":5.222204284,"remaining_time":54.80313231},
{"learn":[26892.54233],"iteration":87,"passed_time":5.280981417,"remaining_time":54.73017104},
{"learn":[26824.22283],"iteration":88,"passed_time":5.340313078,"remaining_time":54.66320466},
{"learn":[26737.30371],"iteration":89,"passed_time":5.394273271,"remaining_time":54.54209641},
{"learn":[26639.35885],"iteration":90,"passed_time":5.455032895,"remaining_time":54.49038353},
{"learn":[26571.18576],"iteration":91,"passed_time":5.508760833,"remaining_time":54.36907431},
{"learn":[26498.92431],"iteration":92,"passed_time":5.564786544,"remaining_time":54.27162791},
{"learn":[26424.38886],"iteration":93,"passed_time":5.624074429,"remaining_time":54.2065046},
{"learn":[26357.78082],"iteration":94,"passed_time":5.680318941,"remaining_time":54.11251201},
{"learn":[26275.04713],"iteration":95,"passed_time":5.734769376,"remaining_time":54.00241162},
{"learn":[26171.09145],"iteration":96,"passed_time":5.788856546,"remaining_time":53.89007692},
{"learn":[26101.25909],"iteration":97,"passed_time":5.839592166,"remaining_time":53.748083},
{"learn":[26041.70652],"iteration":98,"passed_time":5.894281816,"remaining_time":53.64391835},
{"learn":[26012.27575],"iteration":99,"passed_time":5.955368912,"remaining_time":53.59832021},
{"learn":[25952.88654],"iteration":100,"passed_time":6.012802238,"remaining_time":53.51989319},
{"learn":[25831.93866],"iteration":101,"passed_time":6.064150304,"remaining_time":53.38830366},
{"learn":[25772.28462],"iteration":102,"passed_time":6.116135937,"remaining_time":53.26382461},
{"learn":[25717.68753],"iteration":103,"passed_time":6.169597426,"remaining_time":53.15345475},
{"learn":[25655.76096],"iteration":104,"passed_time":6.225780577,"remaining_time":53.06736778},
{"learn":[25611.55937],"iteration":105,"passed_time":6.285015867,"remaining_time":53.00758665},
{"learn":[25568.0035],"iteration":106,"passed_time":6.338440805,"remaining_time":52.89932373},
{"learn":[25537.04362],"iteration":107,"passed_time":6.39787218,"remaining_time":52.84168505},
{"learn":[25454.46868],"iteration":108,"passed_time":6.456491014,"remaining_time":52.7773715},
{"learn":[25414.9273],"iteration":109,"passed_time":6.507929028,"remaining_time":52.65506214},
{"learn":[25390.72648],"iteration":110,"passed_time":6.560385103,"remaining_time":52.54218339},
{"learn":[25330.73647],"iteration":111,"passed_time":6.616962104,"remaining_time":52.46305668},
{"learn":[25269.08496],"iteration":112,"passed_time":6.674609054,"remaining_time":52.3927277},
{"learn":[25227.85153],"iteration":113,"passed_time":6.731644345,"remaining_time":52.31786745},
{"learn":[25188.0866],"iteration":114,"passed_time":6.78717816,"remaining_time":52.23176236},
{"learn":[25170.01787],"iteration":115,"passed_time":6.842107408,"remaining_time":52.14157714},
{"learn":[25076.30467],"iteration":116,"passed_time":6.895308093,"remaining_time":52.03894911},
{"learn":[25006.10732],"iteration":117,"passed_time":6.952796543,"remaining_time":51.96920806},
{"learn":[24931.75431],"iteration":118,"passed_time":7.015104498,"remaining_time":51.93535347},
{"learn":[24885.88472],"iteration":119,"passed_time":7.071415521,"remaining_time":51.85704716},
{"learn":[24854.54658],"iteration":120,"passed_time":7.169018022,"remaining_time":52.0790648},
{"learn":[24796.81831],"iteration":121,"passed_time":7.228086058,"remaining_time":52.01852098},
{"learn":[24762.2548],"iteration":122,"passed_time":7.281653107,"remaining_time":51.91877866},
{"learn":[24688.87525],"iteration":123,"passed_time":7.337193084,"remaining_time":51.83371888},
{"learn":[24648.94108],"iteration":124,"passed_time":7.389976737,"remaining_time":51.72983716},
{"learn":[24591.86261],"iteration":125,"passed_time":7.449698196,"remaining_time":51.67489066},
{"learn":[24550.28781],"iteration":126,"passed_time":7.508411462,"remaining_time":51.61293863},
{"learn":[24460.76805],"iteration":127,"passed_time":7.565426834,"remaining_time":51.5394703},
{"learn":[24414.99624],"iteration":128,"passed_time":7.617369956,"remaining_time":51.43200955},
{"learn":[24389.20473],"iteration":129,"passed_time":7.675433238,"remaining_time":51.3663609},
{"learn":[24330.10609],"iteration":130,"passed_time":7.73456024,"remaining_time":51.30788434},
{"learn":[24303.19022],"iteration":131,"passed_time":7.795161971,"remaining_time":51.25909538},
{"learn":[24265.30591],"iteration":132,"passed_time":7.85443736,"remaining_time":51.20148264},
{"learn":[24207.78601],"iteration":133,"passed_time":7.909703888,"remaining_time":51.11793707},
{"learn":[24115.65536],"iteration":134,"passed_time":7.971289643,"remaining_time":51.0753003},
{"learn":[24046.77466],"iteration":135,"passed_time":8.026392114,"remaining_time":50.99119696},
{"learn":[23996.06672],"iteration":136,"passed_time":8.08023806,"remaining_time":50.8996018},
{"learn":[23957.80721],"iteration":137,"passed_time":8.137624291,"remaining_time":50.83066767},
{"learn":[23903.00866],"iteration":138,"passed_time":8.198794662,"remaining_time":50.7853396},
{"learn":[23868.87869],"iteration":139,"passed_time":8.255496171,"remaining_time":50.71233362},
{"learn":[23831.58112],"iteration":140,"passed_time":8.308647451,"remaining_time":50.61793021},
{"learn":[23789.36376],"iteration":141,"passed_time":8.364691874,"remaining_time":50.54158893},
{"learn":[23746.60098],"iteration":142,"passed_time":8.418009724,"remaining_time":50.44919114},
{"learn":[23690.10424],"iteration":143,"passed_time":8.474200662,"remaining_time":50.37441504},
{"learn":[23644.529],"iteration":144,"passed_time":8.536644774,"remaining_time":50.33676746},
{"learn":[23585.2408],"iteration":145,"passed_time":8.595342263,"remaining_time":50.27686502},
{"learn":[23530.3347],"iteration":146,"passed_time":8.649614256,"remaining_time":50.19129905},
{"learn":[23479.64876],"iteration":147,"passed_time":8.706395079,"remaining_time":50.1205987},
{"learn":[23440.88664],"iteration":148,"passed_time":8.758796029,"remaining_time":50.02506994},
{"learn":[23380.48205],"iteration":149,"passed_time":8.815158495,"remaining_time":49.9525648},
{"learn":[23362.1086],"iteration":150,"passed_time":8.877544402,"remaining_time":49.91414038},
{"learn":[23300.93672],"iteration":151,"passed_time":8.93369868,"remaining_time":49.84063474},
{"learn":[23244.11243],"iteration":152,"passed_time":8.989438031,"remaining_time":49.7650589},
{"learn":[23188.56913],"iteration":153,"passed_time":9.042286717,"remaining_time":49.67386079},
{"learn":[23131.16983],"iteration":154,"passed_time":9.0935574,"remaining_time":49.57455486},
{"learn":[23088.44299],"iteration":155,"passed_time":9.143972512,"remaining_time":49.4712359},
{"learn":[23057.20903],"iteration":156,"passed_time":9.207275317,"remaining_time":49.4377904},
{"learn":[23018.79084],"iteration":157,"passed_time":9.265304125,"remaining_time":49.37586122},
{"learn":[22981.46471],"iteration":158,"passed_time":9.324771458,"remaining_time":49.32158991},
{"learn":[22961.71873],"iteration":159,"passed_time":9.379392108,"remaining_time":49.24180857},
{"learn":[22929.96984],"iteration":160,"passed_time":9.43091218,"remaining_time":49.14618211},
{"learn":[22888.29007],"iteration":161,"passed_time":9.48745561,"remaining_time":49.07708519},
{"learn":[22850.63058],"iteration":162,"passed_time":9.547749194,"remaining_time":49.02739924},
{"learn":[22818.16965],"iteration":163,"passed_time":9.605782711,"remaining_time":48.96606309},
{"learn":[22798.13183],"iteration":164,"passed_time":9.660698601,"remaining_time":48.88898989},
{"learn":[22759.60759],"iteration":165,"passed_time":9.719247054,"remaining_time":48.83043399},
{"learn":[22746.68211],"iteration":166,"passed_time":9.770805902,"remaining_time":48.73701387},
{"learn":[22697.04954],"iteration":167,"passed_time":9.826398197,"remaining_time":48.66406726},
{"learn":[22660.71378],"iteration":168,"passed_time":9.883817857,"remaining_time":48.60031147},
{"learn":[22600.62115],"iteration":169,"passed_time":9.943356183,"remaining_time":48.5469743},
{"learn":[22576.07761],"iteration":170,"passed_time":9.999473675,"remaining_time":48.47698057},
{"learn":[22537.40234],"iteration":171,"passed_time":10.06016432,"remaining_time":48.42916313},
{"learn":[22494.79281],"iteration":172,"passed_time":10.11540947,"remaining_time":48.35516552},
{"learn":[22465.8593],"iteration":173,"passed_time":10.16881263,"remaining_time":48.27263926},
{"learn":[22412.4195],"iteration":174,"passed_time":10.23123255,"remaining_time":48.23295346},
{"learn":[22379.96988],"iteration":175,"passed_time":10.29102745,"remaining_time":48.18071943},
{"learn":[22353.00188],"iteration":176,"passed_time":10.34773494,"remaining_time":48.11404436},
{"learn":[22315.60087],"iteration":177,"passed_time":10.4052575,"remaining_time":48.05124533},
{"learn":[22293.31611],"iteration":178,"passed_time":10.45812302,"remaining_time":47.96714527},
{"learn":[22268.00456],"iteration":179,"passed_time":10.50904589,"remaining_time":47.87454237},
{"learn":[22229.50935],"iteration":180,"passed_time":10.56354299,"remaining_time":47.79857299},
{"learn":[22188.72132],"iteration":181,"passed_time":10.61770174,"remaining_time":47.72131882},
{"learn":[22157.70437],"iteration":182,"passed_time":10.67945301,"remaining_time":47.67821369},
{"learn":[22135.48818],"iteration":183,"passed_time":10.74036938,"remaining_time":47.63120334},
{"learn":[22113.85102],"iteration":184,"passed_time":10.79306072,"remaining_time":47.54780802},
{"learn":[22083.05869],"iteration":185,"passed_time":10.84374183,"remaining_time":47.45594544},
{"learn":[22061.27301],"iteration":186,"passed_time":10.90279715,"remaining_time":47.40093094},
{"learn":[22033.41692],"iteration":187,"passed_time":10.95740619,"remaining_time":47.3266693},
{"learn":[22012.65701],"iteration":188,"passed_time":11.01651411,"remaining_time":47.27192035},
{"learn":[21983.77402],"iteration":189,"passed_time":11.07343545,"remaining_time":47.20780375},
{"learn":[21961.21322],"iteration":190,"passed_time":11.13158889,"remaining_time":47.14898122},
{"learn":[21919.86472],"iteration":191,"passed_time":11.18780286,"remaining_time":47.0820037},
{"learn":[21894.64559],"iteration":192,"passed_time":11.24229158,"remaining_time":47.00792385},
{"learn":[21844.07784],"iteration":193,"passed_time":11.29343077,"remaining_time":46.9201299},
{"learn":[21811.1043],"iteration":194,"passed_time":11.35106031,"remaining_time":46.85950539},
{"learn":[21803.14113],"iteration":195,"passed_time":11.40919702,"remaining_time":46.80099184},
{"learn":[21766.16998],"iteration":196,"passed_time":11.46341918,"remaining_time":46.7265259},
{"learn":[21733.61917],"iteration":197,"passed_time":11.51720627,"remaining_time":46.65050218},
{"learn":[21697.34148],"iteration":198,"passed_time":11.57391433,"remaining_time":46.58645919},
{"learn":[21687.59779],"iteration":199,"passed_time":11.62804087,"remaining_time":46.51216348},
{"learn":[21658.43166],"iteration":200,"passed_time":11.67962294,"remaining_time":46.42795389},
{"learn":[21623.30313],"iteration":201,"passed_time":11.74466404,"remaining_time":46.39723714},
{"learn":[21611.22217],"iteration":202,"passed_time":11.8046232,"remaining_time":46.34623001},
{"learn":[21538.96292],"iteration":203,"passed_time":11.85904745,"remaining_time":46.27353811},
{"learn":[21518.15813],"iteration":204,"passed_time":11.91423603,"remaining_time":46.20398852},
{"learn":[21490.2394],"iteration":205,"passed_time":11.96702661,"remaining_time":46.12533557},
{"learn":[21456.48464],"iteration":206,"passed_time":12.02256094,"remaining_time":46.0574436},
{"learn":[21413.0944],"iteration":207,"passed_time":12.08651597,"remaining_time":46.0217339},
{"learn":[21374.51745],"iteration":208,"passed_time":12.13889844,"remaining_time":45.94195532},
{"learn":[21338.90613],"iteration":209,"passed_time":12.19859026,"remaining_time":45.88993479},
{"learn":[21326.77121],"iteration":210,"passed_time":12.2550001,"remaining_time":45.82556909},
{"learn":[21285.5329],"iteration":211,"passed_time":12.30909015,"remaining_time":45.75265585},
{"learn":[21258.25244],"iteration":212,"passed_time":12.36050287,"remaining_time":45.67002705},
{"learn":[21234.7499],"iteration":213,"passed_time":12.41975175,"remaining_time":45.61647138},
{"learn":[21192.42565],"iteration":214,"passed_time":12.48185733,"remaining_time":45.57329305},
{"learn":[21177.92011],"iteration":215,"passed_time":12.53733001,"remaining_time":45.50586448},
{"learn":[21127.70165],"iteration":216,"passed_time":12.59735193,"remaining_time":45.45496111},
{"learn":[21098.26788],"iteration":217,"passed_time":12.65010986,"remaining_time":45.37791702},
{"learn":[21078.13667],"iteration":218,"passed_time":12.70229923,"remaining_time":45.29906713},
{"learn":[21051.70695],"iteration":219,"passed_time":12.75575934,"remaining_time":45.22496494},
{"learn":[21018.16521],"iteration":220,"passed_time":12.8161349,"remaining_time":45.17542573},
{"learn":[20986.18512],"iteration":221,"passed_time":12.86717371,"remaining_time":45.09306822},
{"learn":[20942.54632],"iteration":222,"passed_time":12.92611396,"remaining_time":45.03852262},
{"learn":[20924.15792],"iteration":223,"passed_time":12.97930833,"remaining_time":44.96403243},
{"learn":[20870.44987],"iteration":224,"passed_time":13.03202375,"remaining_time":44.88808181},
{"learn":[20859.21199],"iteration":225,"passed_time":13.08265993,"remaining_time":44.80521586},
{"learn":[20787.55045],"iteration":226,"passed_time":13.13795417,"remaining_time":44.73849593},
{"learn":[20763.64451],"iteration":227,"passed_time":13.19658606,"remaining_time":44.68317738},
{"learn":[20745.94536],"iteration":228,"passed_time":13.25407068,"remaining_time":44.62396723},
{"learn":[20726.27702],"iteration":229,"passed_time":13.30675549,"remaining_time":44.54870316},
{"learn":[20706.30157],"iteration":230,"passed_time":13.35867962,"remaining_time":44.47110227},
{"learn":[20661.16128],"iteration":231,"passed_time":13.41505517,"remaining_time":44.4084585},
{"learn":[20643.13335],"iteration":232,"passed_time":13.46949951,"remaining_time":44.33951128},
{"learn":[20625.03504],"iteration":233,"passed_time":13.5232748,"remaining_time":44.26849785},
{"learn":[20578.76158],"iteration":234,"passed_time":13.58235417,"remaining_time":44.21489763},
{"learn":[20531.69223],"iteration":235,"passed_time":13.63520873,"remaining_time":44.14109944},
{"learn":[20502.62508],"iteration":236,"passed_time":13.6859307,"remaining_time":44.06061234},
{"learn":[20478.36555],"iteration":237,"passed_time":13.74113432,"remaining_time":43.99472417},
{"learn":[20448.74201],"iteration":238,"passed_time":13.79473491,"remaining_time":43.9238212},
{"learn":[20427.13805],"iteration":239,"passed_time":13.85532967,"remaining_time":43.87521061},
{"learn":[20413.65167],"iteration":240,"passed_time":13.9113795,"remaining_time":43.81218688},
{"learn":[20402.0188],"iteration":241,"passed_time":13.96408447,"remaining_time":43.73874392},
{"learn":[20375.53738],"iteration":242,"passed_time":14.01752277,"remaining_time":43.66775613},
{"learn":[20342.24261],"iteration":243,"passed_time":14.0736756,"remaining_time":43.60532276},
{"learn":[20320.68101],"iteration":244,"passed_time":14.12719875,"remaining_time":43.53483697},
{"learn":[20305.01206],"iteration":245,"passed_time":14.18260291,"remaining_time":43.47025444},
{"learn":[20292.47245],"iteration":246,"passed_time":14.24193527,"remaining_time":43.41772169},
{"learn":[20274.6612],"iteration":247,"passed_time":14.30014469,"remaining_time":43.36172907},
{"learn":[20264.40039],"iteration":248,"passed_time":14.35922982,"remaining_time":43.30835981},
{"learn":[20227.23652],"iteration":249,"passed_time":14.4113971,"remaining_time":43.23419129},
{"learn":[20200.85741],"iteration":250,"passed_time":14.49293689,"remaining_time":43.24784754},
{"learn":[20185.81441],"iteration":251,"passed_time":14.55010675,"remaining_time":43.18841211},
{"learn":[20156.62184],"iteration":252,"passed_time":14.61284659,"remaining_time":43.14544032},
{"learn":[20119.00793],"iteration":253,"passed_time":14.66491883,"remaining_time":43.07098207},
{"learn":[20105.46011],"iteration":254,"passed_time":14.72033673,"remaining_time":43.00647399},
{"learn":[20077.95733],"iteration":255,"passed_time":14.77659843,"remaining_time":42.94448918},
{"learn":[20059.06587],"iteration":256,"passed_time":14.82708898,"remaining_time":42.86586425},
{"learn":[20036.72482],"iteration":257,"passed_time":14.88037418,"remaining_time":42.79549474},
{"learn":[20008.70887],"iteration":258,"passed_time":14.94118617,"remaining_time":42.74679133},
{"learn":[19983.93402],"iteration":259,"passed_time":14.99863385,"remaining_time":42.68841941},
{"learn":[19960.30724],"iteration":260,"passed_time":15.05246311,"remaining_time":42.61980934},
{"learn":[19937.2219],"iteration":261,"passed_time":15.10461453,"remaining_time":42.54658596},
{"learn":[19909.56028],"iteration":262,"passed_time":15.16006045,"remaining_time":42.48275494},
{"learn":[19884.80368],"iteration":263,"passed_time":15.21319055,"remaining_time":42.41253124},
{"learn":[19846.14859],"iteration":264,"passed_time":15.26469496,"remaining_time":42.33792753},
{"learn":[19825.10039],"iteration":265,"passed_time":15.32391025,"remaining_time":42.28477491},
{"learn":[19813.40955],"iteration":266,"passed_time":15.3797607,"remaining_time":42.2223393},
{"learn":[19788.36159],"iteration":267,"passed_time":15.43704157,"remaining_time":42.16385982},
{"learn":[19764.56128],"iteration":268,"passed_time":15.49172546,"remaining_time":42.098332},
{"learn":[19745.17676],"iteration":269,"passed_time":15.54384241,"remaining_time":42.02594429},
{"learn":[19696.10266],"iteration":270,"passed_time":15.59645132,"remaining_time":41.95502956},
{"learn":[19668.5417],"iteration":271,"passed_time":15.65538119,"remaining_time":41.90116731},
{"learn":[19650.60717],"iteration":272,"passed_time":15.71471794,"remaining_time":41.84835143},
{"learn":[19628.26554],"iteration":273,"passed_time":15.78774226,"remaining_time":41.83175504},
{"learn":[19594.5773],"iteration":274,"passed_time":15.84149111,"remaining_time":41.7639311},
{"learn":[19578.23265],"iteration":275,"passed_time":15.89436653,"remaining_time":41.693918},
{"learn":[19549.07303],"iteration":276,"passed_time":15.95065872,"remaining_time":41.63294677},
{"learn":[19486.72755],"iteration":277,"passed_time":16.00619232,"remaining_time":41.57003904},
{"learn":[19451.53318],"iteration":278,"passed_time":16.06136678,"remaining_time":41.50625608},
{"learn":[19436.53861],"iteration":279,"passed_time":16.1216535,"remaining_time":41.45568043},
{"learn":[19397.31371],"iteration":280,"passed_time":16.17500588,"remaining_time":41.38729263},
{"learn":[19382.71844],"iteration":281,"passed_time":16.2284454,"remaining_time":41.31923333},
{"learn":[19368.34818],"iteration":282,"passed_time":16.28588168,"remaining_time":41.26140341},
{"learn":[19350.10925],"iteration":283,"passed_time":16.34297238,"remaining_time":41.20270501},
{"learn":[19298.93075],"iteration":284,"passed_time":16.40291912,"remaining_time":41.15118305},
{"learn":[19285.4569],"iteration":285,"passed_time":16.45865735,"remaining_time":41.08909563},
{"learn":[19265.05061],"iteration":286,"passed_time":16.51590725,"remaining_time":41.0308079},
{"learn":[19247.99444],"iteration":287,"passed_time":16.57168662,"remaining_time":40.96889192},
{"learn":[19237.11993],"iteration":288,"passed_time":16.62362754,"remaining_time":40.89757502},
{"learn":[19215.12413],"iteration":289,"passed_time":16.67679804,"remaining_time":40.82940211},
{"learn":[19186.21387],"iteration":290,"passed_time":16.73332193,"remaining_time":40.76950258},
{"learn":[19158.73818],"iteration":291,"passed_time":16.79685829,"remaining_time":40.72662901},
{"learn":[19145.17355],"iteration":292,"passed_time":16.85761192,"remaining_time":40.67689976},
{"learn":[19113.83189],"iteration":293,"passed_time":16.90933755,"remaining_time":40.60541602},
{"learn":[19092.51071],"iteration":294,"passed_time":16.96395831,"remaining_time":40.54098511},
{"learn":[19067.2344],"iteration":295,"passed_time":17.02032002,"remaining_time":40.48076112},
{"learn":[19049.6769],"iteration":296,"passed_time":17.07362881,"remaining_time":40.41333689},
{"learn":[19011.66195],"iteration":297,"passed_time":17.13592233,"remaining_time":40.36717274},
{"learn":[18996.94766],"iteration":298,"passed_time":17.19392566,"remaining_time":40.31084243},
{"learn":[18961.71176],"iteration":299,"passed_time":17.25116689,"remaining_time":40.25272274},
{"learn":[18946.14736],"iteration":300,"passed_time":17.30524131,"remaining_time":40.18725473},
{"learn":[18924.13075],"iteration":301,"passed_time":17.35684691,"remaining_time":40.11615611},
{"learn":[18878.09681],"iteration":302,"passed_time":17.40680074,"remaining_time":40.04138653},
{"learn":[18861.66317],"iteration":303,"passed_time":17.46598489,"remaining_time":39.98791277},
{"learn":[18836.1558],"iteration":304,"passed_time":17.52131809,"remaining_time":39.92562646},
{"learn":[18824.77032],"iteration":305,"passed_time":17.57608461,"remaining_time":39.86210038},
{"learn":[18806.5488],"iteration":306,"passed_time":17.63142392,"remaining_time":39.79992434},
{"learn":[18780.87784],"iteration":307,"passed_time":17.68520124,"remaining_time":39.7342833},
{"learn":[18762.02508],"iteration":308,"passed_time":17.73591558,"remaining_time":39.66186948},
{"learn":[18735.11549],"iteration":309,"passed_time":17.79147165,"remaining_time":39.60037239},
{"learn":[18710.15659],"iteration":310,"passed_time":17.85331429,"remaining_time":39.55284099},
{"learn":[18679.0589],"iteration":311,"passed_time":17.90619609,"remaining_time":39.48545804},
{"learn":[18663.53224],"iteration":312,"passed_time":17.96206763,"remaining_time":39.42472991},
{"learn":[18636.78215],"iteration":313,"passed_time":18.01170844,"remaining_time":39.35042035},
{"learn":[18620.69128],"iteration":314,"passed_time":18.06594637,"remaining_time":39.28626433},
{"learn":[18604.5222],"iteration":315,"passed_time":18.11953173,"remaining_time":39.22075856},
{"learn":[18585.04536],"iteration":316,"passed_time":18.17561672,"remaining_time":39.16071363},
{"learn":[18558.17627],"iteration":317,"passed_time":18.22734779,"remaining_time":39.09135596},
{"learn":[18545.22172],"iteration":318,"passed_time":18.28682645,"remaining_time":39.03864832},
{"learn":[18522.83233],"iteration":319,"passed_time":18.33677366,"remaining_time":38.96564402},
{"learn":[18495.40246],"iteration":320,"passed_time":18.38964255,"remaining_time":38.89896353},
{"learn":[18470.09045],"iteration":321,"passed_time":18.44182709,"remaining_time":38.83092784},
{"learn":[18454.22527],"iteration":322,"passed_time":18.49822802,"remaining_time":38.77182777},
{"learn":[18436.85105],"iteration":323,"passed_time":18.55357708,"remaining_time":38.71054971},
{"learn":[18433.21043],"iteration":324,"passed_time":18.60926102,"remaining_time":38.65000366},
{"learn":[18399.59836],"iteration":325,"passed_time":18.66013024,"remaining_time":38.57953307},
{"learn":[18374.59843],"iteration":326,"passed_time":18.71051741,"remaining_time":38.50819027},
{"learn":[18362.55429],"iteration":327,"passed_time":18.76288784,"remaining_time":38.44103851},
{"learn":[18353.47874],"iteration":328,"passed_time":18.8177344,"remaining_time":38.37902669},
{"learn":[18343.92805],"iteration":329,"passed_time":18.87387006,"remaining_time":38.31967558},
{"learn":[18324.35918],"iteration":330,"passed_time":18.93488805,"remaining_time":38.27021179},
{"learn":[18311.62944],"iteration":331,"passed_time":18.9884438,"remaining_time":38.20566403},
{"learn":[18285.93657],"iteration":332,"passed_time":19.03879355,"remaining_time":38.13476066},
{"learn":[18262.58537],"iteration":333,"passed_time":19.09774132,"remaining_time":38.08112491},
{"learn":[18253.80593],"iteration":334,"passed_time":19.14891801,"remaining_time":38.01203127},
{"learn":[18212.1938],"iteration":335,"passed_time":19.21073652,"remaining_time":37.96407455},
{"learn":[18196.64162],"iteration":336,"passed_time":19.26538777,"remaining_time":37.90193499},
{"learn":[18182.99884],"iteration":337,"passed_time":19.31817574,"remaining_time":37.83619035},
{"learn":[18172.17663],"iteration":338,"passed_time":19.37825762,"remaining_time":37.78474422},
{"learn":[18157.83266],"iteration":339,"passed_time":19.43595422,"remaining_time":37.72861702},
{"learn":[18144.43093],"iteration":340,"passed_time":19.48850182,"remaining_time":37.66252992},
{"learn":[18128.09654],"iteration":341,"passed_time":19.54578541,"remaining_time":37.60563391},
{"learn":[18114.81737],"iteration":342,"passed_time":19.60444047,"remaining_time":37.55136264},
{"learn":[18103.3623],"iteration":343,"passed_time":19.6632565,"remaining_time":37.49737287},
{"learn":[18085.10718],"iteration":344,"passed_time":19.71621568,"remaining_time":37.43223557},
{"learn":[18072.55134],"iteration":345,"passed_time":19.77504482,"remaining_time":37.37826391},
{"learn":[18052.11092],"iteration":346,"passed_time":19.82793101,"remaining_time":37.31308054},
{"learn":[18016.03448],"iteration":347,"passed_time":19.88362673,"remaining_time":37.25323169},
{"learn":[18005.68297],"iteration":348,"passed_time":19.94605537,"remaining_time":37.20596575},
{"learn":[17992.35407],"iteration":349,"passed_time":19.99701662,"remaining_time":37.13731659},
{"learn":[17979.77619],"iteration":350,"passed_time":20.05298772,"remaining_time":37.07803143},
{"learn":[17964.20187],"iteration":351,"passed_time":20.11105247,"remaining_time":37.02261932},
{"learn":[17943.92371],"iteration":352,"passed_time":20.16458117,"remaining_time":36.95887824},
{"learn":[17929.20665],"iteration":353,"passed_time":20.21727574,"remaining_time":36.89367268},
{"learn":[17887.25921],"iteration":354,"passed_time":20.27389204,"remaining_time":36.83566301},
{"learn":[17865.71295],"iteration":355,"passed_time":20.3312058,"remaining_time":36.77892285},
{"learn":[17844.13799],"iteration":356,"passed_time":20.38789017,"remaining_time":36.72104588},
{"learn":[17825.32988],"iteration":357,"passed_time":20.44420075,"remaining_time":36.66250525},
{"learn":[17788.86189],"iteration":358,"passed_time":20.49767937,"remaining_time":36.59892055},
{"learn":[17768.51322],"iteration":359,"passed_time":20.55173123,"remaining_time":36.53641108},
{"learn":[17757.44946],"iteration":360,"passed_time":20.61009272,"remaining_time":36.48157686},
{"learn":[17744.96036],"iteration":361,"passed_time":20.67107352,"remaining_time":36.43133952},
{"learn":[17717.44861],"iteration":362,"passed_time":20.72356412,"remaining_time":36.36614419},
{"learn":[17711.0753],"iteration":363,"passed_time":20.78179848,"remaining_time":36.31105449},
{"learn":[17700.97632],"iteration":364,"passed_time":20.8336758,"remaining_time":36.24488803},
{"learn":[17686.03759],"iteration":365,"passed_time":20.88914232,"remaining_time":36.18501703},
{"learn":[17666.48907],"iteration":366,"passed_time":20.9434965,"remaining_time":36.12325145},
{"learn":[17654.74159],"iteration":367,"passed_time":20.99867877,"remaining_time":36.06294831},
{"learn":[17643.17426],"iteration":368,"passed_time":21.05512962,"remaining_time":36.00484224},
{"learn":[17633.02668],"iteration":369,"passed_time":21.1120242,"remaining_time":35.94750066},
{"learn":[17598.97925],"iteration":370,"passed_time":21.16278415,"remaining_time":35.87976073},
{"learn":[17566.84447],"iteration":371,"passed_time":21.21840725,"remaining_time":35.82032192},
{"learn":[17544.20725],"iteration":372,"passed_time":21.272646,"remaining_time":35.75857652},
{"learn":[17515.86453],"iteration":373,"passed_time":21.32805336,"remaining_time":35.69882729},
{"learn":[17480.75471],"iteration":374,"passed_time":21.38553477,"remaining_time":35.64255795},
{"learn":[17465.28731],"iteration":375,"passed_time":21.44303841,"remaining_time":35.58631907},
{"learn":[17454.56248],"iteration":376,"passed_time":21.49386642,"remaining_time":35.51904185},
{"learn":[17449.58376],"iteration":377,"passed_time":21.54480167,"remaining_time":35.45202814},
{"learn":[17415.44664],"iteration":378,"passed_time":21.60246608,"remaining_time":35.39612517},
{"learn":[17397.78931],"iteration":379,"passed_time":21.65644308,"remaining_time":35.33419661},
{"learn":[17391.25033],"iteration":380,"passed_time":21.7372172,"remaining_time":35.31584632},
{"learn":[17368.65536],"iteration":381,"passed_time":21.80236105,"remaining_time":35.27188253},
{"learn":[17345.38855],"iteration":382,"passed_time":21.86045209,"remaining_time":35.21644632},
{"learn":[17343.37667],"iteration":383,"passed_time":21.91267221,"remaining_time":35.15157833},
{"learn":[17310.64874],"iteration":384,"passed_time":21.96763739,"remaining_time":35.09116103},
{"learn":[17302.75119],"iteration":385,"passed_time":22.02898342,"remaining_time":35.04092181},
{"learn":[17290.48023],"iteration":386,"passed_time":22.08510442,"remaining_time":34.98234887},
{"learn":[17277.35989],"iteration":387,"passed_time":22.14682801,"remaining_time":34.93262563},
{"learn":[17265.20206],"iteration":388,"passed_time":22.20349883,"remaining_time":34.87490433},
{"learn":[17234.8681],"iteration":389,"passed_time":22.2577168,"remaining_time":34.81335192},
{"learn":[17225.27691],"iteration":390,"passed_time":22.31410136,"remaining_time":34.75521159},
{"learn":[17194.91135],"iteration":391,"passed_time":22.37015948,"remaining_time":34.69657389},
{"learn":[17190.4187],"iteration":392,"passed_time":22.42083025,"remaining_time":34.6296284},
{"learn":[17176.36195],"iteration":393,"passed_time":22.48086198,"remaining_time":34.57716335},
{"learn":[17162.58618],"iteration":394,"passed_time":22.53463892,"remaining_time":34.51507986},
{"learn":[17153.97909],"iteration":395,"passed_time":22.58995002,"remaining_time":34.45537831},
{"learn":[17147.03097],"iteration":396,"passed_time":22.64590505,"remaining_time":34.39667694},
{"learn":[17118.51592],"iteration":397,"passed_time":22.69500206,"remaining_time":34.32761618},
{"learn":[17113.96123],"iteration":398,"passed_time":22.76057579,"remaining_time":34.28347381},
{"learn":[17098.44761],"iteration":399,"passed_time":22.82872867,"remaining_time":34.243093},
{"learn":[17080.8454],"iteration":400,"passed_time":22.88369335,"remaining_time":34.18287361},
{"learn":[17053.20559],"iteration":401,"passed_time":22.93406655,"remaining_time":34.11585024},
{"learn":[17027.2336],"iteration":402,"passed_time":22.98858289,"remaining_time":34.05504711},
{"learn":[17012.20503],"iteration":403,"passed_time":23.04165932,"remaining_time":33.99215088},
{"learn":[16996.8798],"iteration":404,"passed_time":23.09122784,"remaining_time":33.92414954},
{"learn":[16986.66557],"iteration":405,"passed_time":23.15165896,"remaining_time":33.87213158},
{"learn":[16974.30757],"iteration":406,"passed_time":23.20684419,"remaining_time":33.81242901},
{"learn":[16958.94949],"iteration":407,"passed_time":23.2627986,"remaining_time":33.75386463},
{"learn":[16949.17817],"iteration":408,"passed_time":23.31723356,"remaining_time":33.69311745},
{"learn":[16941.46977],"iteration":409,"passed_time":23.36794353,"remaining_time":33.62704069},
{"learn":[16934.1108],"iteration":410,"passed_time":23.4229052,"remaining_time":33.56713178},
{"learn":[16897.48554],"iteration":411,"passed_time":23.48414026,"remaining_time":33.51620017},
{"learn":[16893.97598],"iteration":412,"passed_time":23.54093924,"remaining_time":33.45891365},
{"learn":[16888.84199],"iteration":413,"passed_time":23.59449531,"remaining_time":33.39703926},
{"learn":[16882.23955],"iteration":414,"passed_time":23.65291409,"remaining_time":33.34205961},
{"learn":[16831.63186],"iteration":415,"passed_time":23.70937223,"remaining_time":33.28431102},
{"learn":[16814.25905],"iteration":416,"passed_time":23.76071281,"remaining_time":33.21941383},
{"learn":[16803.41445],"iteration":417,"passed_time":23.81851358,"remaining_time":33.16357633},
{"learn":[16791.88963],"iteration":418,"passed_time":23.8758394,"remaining_time":33.10707087},
{"learn":[16779.88281],"iteration":419,"passed_time":23.9336607,"remaining_time":33.05124573},
{"learn":[16750.45008],"iteration":420,"passed_time":23.99132487,"remaining_time":32.99519501},
{"learn":[16729.57395],"iteration":421,"passed_time":24.03913862,"remaining_time":32.92564484},
{"learn":[16723.75148],"iteration":422,"passed_time":24.09378918,"remaining_time":32.8655233},
{"learn":[16718.46334],"iteration":423,"passed_time":24.14692849,"remaining_time":32.80337456},
{"learn":[16701.43741],"iteration":424,"passed_time":24.20695564,"remaining_time":32.75058704},
{"learn":[16685.22834],"iteration":425,"passed_time":24.25961522,"remaining_time":32.68783835},
{"learn":[16664.9204],"iteration":426,"passed_time":24.31774701,"remaining_time":32.63248018},
{"learn":[16662.15231],"iteration":427,"passed_time":24.37164568,"remaining_time":32.57145171},
{"learn":[16640.41944],"iteration":428,"passed_time":24.42169091,"remaining_time":32.50532753},
{"learn":[16628.9709],"iteration":429,"passed_time":24.47538167,"remaining_time":32.44411059},
{"learn":[16603.17166],"iteration":430,"passed_time":24.53232313,"remaining_time":32.38722009},
{"learn":[16583.10059],"iteration":431,"passed_time":24.58930591,"remaining_time":32.33038369},
{"learn":[16561.14389],"iteration":432,"passed_time":24.64767284,"remaining_time":32.27535912},
{"learn":[16548.15549],"iteration":433,"passed_time":24.698935,"remaining_time":32.21105348},
{"learn":[16538.26211],"iteration":434,"passed_time":24.75040647,"remaining_time":32.14707967},
{"learn":[16526.46599],"iteration":435,"passed_time":24.80658074,"remaining_time":32.08924665},
{"learn":[16510.85268],"iteration":436,"passed_time":24.85879696,"remaining_time":32.02632194},
{"learn":[16497.93856],"iteration":437,"passed_time":24.91821134,"remaining_time":31.97268213},
{"learn":[16471.32712],"iteration":438,"passed_time":24.97785474,"remaining_time":31.91930867},
{"learn":[16461.96579],"iteration":439,"passed_time":25.03297854,"remaining_time":31.8601545},
{"learn":[16454.49212],"iteration":440,"passed_time":25.0847476,"remaining_time":31.79676623},
{"learn":[16435.03573],"iteration":441,"passed_time":25.13688999,"remaining_time":31.73390185},
{"learn":[16406.09328],"iteration":442,"passed_time":25.19013295,"remaining_time":31.67246965},
{"learn":[16392.99313],"iteration":443,"passed_time":25.25003901,"remaining_time":31.61941822},
{"learn":[16368.42316],"iteration":444,"passed_time":25.30423781,"remaining_time":31.55921794},
{"learn":[16354.28692],"iteration":445,"passed_time":25.36044753,"remaining_time":31.50154244},
{"learn":[16342.85027],"iteration":446,"passed_time":25.4150788,"remaining_time":31.44192075},
{"learn":[16327.80204],"iteration":447,"passed_time":25.46993117,"remaining_time":31.38259377},
{"learn":[16304.48094],"iteration":448,"passed_time":25.52635224,"remaining_time":31.32521176},
{"learn":[16292.44777],"iteration":449,"passed_time":25.58531687,"remaining_time":31.27094284},
{"learn":[16283.46793],"iteration":450,"passed_time":25.64522338,"remaining_time":31.21779964},
{"learn":[16274.5712],"iteration":451,"passed_time":25.69784022,"remaining_time":31.15578859},
{"learn":[16267.47281],"iteration":452,"passed_time":25.7497101,"remaining_time":31.09291705},
{"learn":[16260.66364],"iteration":453,"passed_time":25.80572309,"remaining_time":31.03507666},
{"learn":[16243.65801],"iteration":454,"passed_time":25.85748941,"remaining_time":30.97215765},
{"learn":[16232.5753],"iteration":455,"passed_time":25.9158959,"remaining_time":30.91720915},
{"learn":[16206.52543],"iteration":456,"passed_time":25.97027303,"remaining_time":30.85745789},
{"learn":[16185.95945],"iteration":457,"passed_time":26.02404244,"remaining_time":30.79701092},
{"learn":[16181.16563],"iteration":458,"passed_time":26.06742343,"remaining_time":30.72434874},
{"learn":[16161.13663],"iteration":459,"passed_time":26.11959919,"remaining_time":30.66213818},
{"learn":[16156.15503],"iteration":460,"passed_time":26.1699058,"remaining_time":30.59778574},
{"learn":[16145.96976],"iteration":461,"passed_time":26.22657386,"remaining_time":30.54090203},
{"learn":[16141.73565],"iteration":462,"passed_time":26.30310587,"remaining_time":30.50705799},
{"learn":[16107.63383],"iteration":463,"passed_time":26.38063772,"remaining_time":30.47418495},
{"learn":[16098.40966],"iteration":464,"passed_time":26.43322283,"remaining_time":30.41241767},
{"learn":[16087.69782],"iteration":465,"passed_time":26.49059286,"remaining_time":30.35617293},
{"learn":[16077.93788],"iteration":466,"passed_time":26.54923658,"remaining_time":30.30137708},
{"learn":[16046.63211],"iteration":467,"passed_time":26.60096944,"remaining_time":30.23870885},
{"learn":[16032.46242],"iteration":468,"passed_time":26.6628071,"remaining_time":30.18752786},
{"learn":[16010.54276],"iteration":469,"passed_time":26.71791128,"remaining_time":30.12870847},
{"learn":[15993.79018],"iteration":470,"passed_time":26.77525916,"remaining_time":30.07242483},
{"learn":[15983.11336],"iteration":471,"passed_time":26.83222932,"remaining_time":30.01571415},
{"learn":[15967.14683],"iteration":472,"passed_time":26.88315096,"remaining_time":29.95226333},
{"learn":[15951.26096],"iteration":473,"passed_time":26.93562153,"remaining_time":29.89058423},
{"learn":[15928.16689],"iteration":474,"passed_time":26.99503351,"remaining_time":29.83661598},
{"learn":[15913.56037],"iteration":475,"passed_time":27.04836128,"remaining_time":29.77592712},
{"learn":[15898.04625],"iteration":476,"passed_time":27.1034582,"remaining_time":29.71720889},
{"learn":[15871.641],"iteration":477,"passed_time":27.15966238,"remaining_time":29.65971498},
{"learn":[15860.02767],"iteration":478,"passed_time":27.21210268,"remaining_time":29.59813256},
{"learn":[15842.47703],"iteration":479,"passed_time":27.26428532,"remaining_time":29.5363091},
{"learn":[15825.09195],"iteration":480,"passed_time":27.32691348,"remaining_time":29.48579645},
{"learn":[15812.4964],"iteration":481,"passed_time":27.38437782,"remaining_time":29.42968404},
{"learn":[15791.99965],"iteration":482,"passed_time":27.44066572,"remaining_time":29.37230679},
{"learn":[15787.57093],"iteration":483,"passed_time":27.49570634,"remaining_time":29.31360428},
{"learn":[15779.59369],"iteration":484,"passed_time":27.54663351,"remaining_time":29.25054898},
{"learn":[15763.83626],"iteration":485,"passed_time":27.60382043,"remaining_time":29.194164},
{"learn":[15749.24308],"iteration":486,"passed_time":27.65904404,"remaining_time":29.13570758},
{"learn":[15744.95619],"iteration":487,"passed_time":27.70825764,"remaining_time":29.07095884},
{"learn":[15735.4722],"iteration":488,"passed_time":27.7591966,"remaining_time":29.00807661},
{"learn":[15719.94097],"iteration":489,"passed_time":27.81684883,"remaining_time":28.95223041},
{"learn":[15702.46203],"iteration":490,"passed_time":27.87094846,"remaining_time":28.89269402},
{"learn":[15693.69414],"iteration":491,"passed_time":27.92298536,"remaining_time":28.83104992},
{"learn":[15688.1891],"iteration":492,"passed_time":27.97738685,"remaining_time":28.77187653},
{"learn":[15679.02946],"iteration":493,"passed_time":28.03236431,"remaining_time":28.71331243},
{"learn":[15670.2136],"iteration":494,"passed_time":28.09257973,"remaining_time":28.66010659},
{"learn":[15657.18331],"iteration":495,"passed_time":28.15019729,"remaining_time":28.60423273},
{"learn":[15647.59386],"iteration":496,"passed_time":28.20386368,"remaining_time":28.54435298},
{"learn":[15639.09836],"iteration":497,"passed_time":28.25371579,"remaining_time":28.48065327},
{"learn":[15634.76228],"iteration":498,"passed_time":28.31149634,"remaining_time":28.42496928},
{"learn":[15623.91191],"iteration":499,"passed_time":28.3648715,"remaining_time":28.3648715},
{"learn":[15617.38022],"iteration":500,"passed_time":28.42306189,"remaining_time":28.30959657},
{"learn":[15591.24286],"iteration":501,"passed_time":28.48490889,"remaining_time":28.25793751},
{"learn":[15582.34996],"iteration":502,"passed_time":28.57250077,"remaining_time":28.23167571},
{"learn":[15558.80406],"iteration":503,"passed_time":28.62577931,"remaining_time":28.17140186},
{"learn":[15540.78633],"iteration":504,"passed_time":28.68014607,"remaining_time":28.11222239},
{"learn":[15528.24798],"iteration":505,"passed_time":28.73530735,"remaining_time":28.05383761},
{"learn":[15514.72524],"iteration":506,"passed_time":28.78648346,"remaining_time":27.99159042},
{"learn":[15498.77535],"iteration":507,"passed_time":28.84672782,"remaining_time":27.93816947},
{"learn":[15487.83272],"iteration":508,"passed_time":28.90193987,"remaining_time":27.87986734},
{"learn":[15480.45466],"iteration":509,"passed_time":28.95991559,"remaining_time":27.82423263},
{"learn":[15464.08734],"iteration":510,"passed_time":29.01758846,"remaining_time":27.76829893},
{"learn":[15452.49005],"iteration":511,"passed_time":29.06816606,"remaining_time":27.70559577},
{"learn":[15439.00241],"iteration":512,"passed_time":29.12307704,"remaining_time":27.64705365},
{"learn":[15432.02215],"iteration":513,"passed_time":29.18224981,"remaining_time":27.59255527},
{"learn":[15426.5906],"iteration":514,"passed_time":29.24980301,"remaining_time":27.54593099},
{"learn":[15410.99466],"iteration":515,"passed_time":29.30422581,"remaining_time":27.48690948},
{"learn":[15396.96897],"iteration":516,"passed_time":29.36162202,"remaining_time":27.43068363},
{"learn":[15385.23734],"iteration":517,"passed_time":29.41425469,"remaining_time":27.37002077},
{"learn":[15370.93163],"iteration":518,"passed_time":29.46694933,"remaining_time":27.30944629},
{"learn":[15364.56433],"iteration":519,"passed_time":29.52311049,"remaining_time":27.25210199},
{"learn":[15347.50148],"iteration":520,"passed_time":29.58013839,"remaining_time":27.1955591},
{"learn":[15341.09873],"iteration":521,"passed_time":29.63976303,"remaining_time":27.1413922},
{"learn":[15325.76371],"iteration":522,"passed_time":29.69828279,"remaining_time":27.08619674},
{"learn":[15319.78285],"iteration":523,"passed_time":29.75507036,"remaining_time":27.02941506},
{"learn":[15306.40283],"iteration":524,"passed_time":29.80596732,"remaining_time":26.96730377},
{"learn":[15295.58031],"iteration":525,"passed_time":29.86084191,"remaining_time":26.90881952},
{"learn":[15272.25889],"iteration":526,"passed_time":29.92228941,"remaining_time":26.85624837},
{"learn":[15255.2372],"iteration":527,"passed_time":29.97573128,"remaining_time":26.79648705},
{"learn":[15241.47481],"iteration":528,"passed_time":30.0326883,"remaining_time":26.73987938},
{"learn":[15228.1966],"iteration":529,"passed_time":30.08381138,"remaining_time":26.67809689},
{"learn":[15224.77189],"iteration":530,"passed_time":30.13833427,"remaining_time":26.61935739},
{"learn":[15207.96378],"iteration":531,"passed_time":30.1923231,"remaining_time":26.56016393},
{"learn":[15197.14796],"iteration":532,"passed_time":30.25022811,"remaining_time":26.50442125},
{"learn":[15191.8574],"iteration":533,"passed_time":30.30712492,"remaining_time":26.44779066},
{"learn":[15184.32298],"iteration":534,"passed_time":30.36602124,"remaining_time":26.39289697},
{"learn":[15167.17063],"iteration":535,"passed_time":30.41978157,"remaining_time":26.33354226},
{"learn":[15158.18109],"iteration":536,"passed_time":30.47396661,"remaining_time":26.27457456},
{"learn":[15154.46012],"iteration":537,"passed_time":30.52956459,"remaining_time":26.21683799},
{"learn":[15140.26715],"iteration":538,"passed_time":30.58159422,"remaining_time":26.15605739},
{"learn":[15131.55426],"iteration":539,"passed_time":30.64522141,"remaining_time":26.10518861},
{"learn":[15116.87698],"iteration":540,"passed_time":30.70742889,"remaining_time":26.05306813},
{"learn":[15104.45626],"iteration":541,"passed_time":30.81003557,"remaining_time":26.03504851},
{"learn":[15092.26475],"iteration":542,"passed_time":30.86456174,"remaining_time":25.97625178},
{"learn":[15090.15371],"iteration":543,"passed_time":30.93572075,"remaining_time":25.93141298},
{"learn":[15078.89978],"iteration":544,"passed_time":30.99136992,"remaining_time":25.87352902},
{"learn":[15074.11876],"iteration":545,"passed_time":31.0508272,"remaining_time":25.81881968},
{"learn":[15063.13734],"iteration":546,"passed_time":31.11128654,"remaining_time":25.76492285},
{"learn":[15049.93197],"iteration":547,"passed_time":31.16768643,"remaining_time":25.70765377},
{"learn":[15034.58999],"iteration":548,"passed_time":31.2289849,"remaining_time":25.654412},
{"learn":[15022.21325],"iteration":549,"passed_time":31.29378393,"remaining_time":25.60400503},
{"learn":[15003.36457],"iteration":550,"passed_time":31.35302904,"remaining_time":25.54902003},
{"learn":[14991.44869],"iteration":551,"passed_time":31.40885612,"remaining_time":25.49124555},
{"learn":[14976.97094],"iteration":552,"passed_time":31.47706841,"remaining_time":25.4434893},
{"learn":[14969.34733],"iteration":553,"passed_time":31.54193778,"remaining_time":25.39296796},
{"learn":[14952.05271],"iteration":554,"passed_time":31.60212763,"remaining_time":25.33864287},
{"learn":[14942.45405],"iteration":555,"passed_time":31.66710159,"remaining_time":25.2881171},
{"learn":[14924.28889],"iteration":556,"passed_time":31.72251083,"remaining_time":25.22993231},
{"learn":[14910.40926],"iteration":557,"passed_time":31.77845955,"remaining_time":25.17218481},
{"learn":[14902.43329],"iteration":558,"passed_time":31.84350005,"remaining_time":25.12161632},
{"learn":[14874.63407],"iteration":559,"passed_time":31.90564133,"remaining_time":25.06871819},
{"learn":[14869.85136],"iteration":560,"passed_time":31.9624487,"remaining_time":25.01161316},
{"learn":[14858.92985],"iteration":561,"passed_time":32.02595148,"remaining_time":24.95972731},
{"learn":[14846.16927],"iteration":562,"passed_time":32.07711593,"remaining_time":24.8982232},
{"learn":[14839.83895],"iteration":563,"passed_time":32.18785586,"remaining_time":24.88281056},
{"learn":[14827.85521],"iteration":564,"passed_time":32.25000052,"remaining_time":24.82964642},
{"learn":[14803.1429],"iteration":565,"passed_time":32.32548496,"remaining_time":24.78667928},
{"learn":[14790.06684],"iteration":566,"passed_time":32.40662849,"remaining_time":24.74791911},
{"learn":[14775.22483],"iteration":567,"passed_time":32.50001982,"remaining_time":24.71832494},
{"learn":[14770.93394],"iteration":568,"passed_time":32.56211155,"remaining_time":24.66479803},
{"learn":[14759.08247],"iteration":569,"passed_time":32.62497169,"remaining_time":24.61182075},
{"learn":[14743.34406],"iteration":570,"passed_time":32.68696589,"remaining_time":24.55815826},
{"learn":[14732.32979],"iteration":571,"passed_time":32.77235581,"remaining_time":24.52197253},
{"learn":[14726.91434],"iteration":572,"passed_time":32.83217598,"remaining_time":24.46656046},
{"learn":[14715.55522],"iteration":573,"passed_time":32.89090615,"remaining_time":24.41032408},
{"learn":[14711.85443],"iteration":574,"passed_time":32.95252969,"remaining_time":24.3562176},
{"learn":[14702.54739],"iteration":575,"passed_time":33.01001067,"remaining_time":24.29903563},
{"learn":[14690.32628],"iteration":576,"passed_time":33.06645445,"remaining_time":24.24109226},
{"learn":[14684.66935],"iteration":577,"passed_time":33.12284194,"remaining_time":24.18311297},
{"learn":[14679.55064],"iteration":578,"passed_time":33.17816063,"remaining_time":24.12436205},
{"learn":[14665.00572],"iteration":579,"passed_time":33.23721807,"remaining_time":24.06833033},
{"learn":[14657.77014],"iteration":580,"passed_time":33.29969467,"remaining_time":24.01475399},
{"learn":[14654.35579],"iteration":581,"passed_time":33.35645493,"remaining_time":23.95704152},
{"learn":[14639.82802],"iteration":582,"passed_time":33.41770878,"remaining_time":23.90254641},
{"learn":[14628.912],"iteration":583,"passed_time":33.47702437,"remaining_time":23.8466475},
{"learn":[14621.99829],"iteration":584,"passed_time":33.53620186,"remaining_time":23.79063893},
{"learn":[14602.67226],"iteration":585,"passed_time":33.59552317,"remaining_time":23.73472115},
{"learn":[14594.46436],"iteration":586,"passed_time":33.65009504,"remaining_time":23.67545017},
{"learn":[14588.70494],"iteration":587,"passed_time":33.71561165,"remaining_time":23.62386394},
{"learn":[14578.68791],"iteration":588,"passed_time":33.77967733,"remaining_time":23.57121797},
{"learn":[14566.31999],"iteration":589,"passed_time":33.83727283,"remaining_time":23.51403705},
{"learn":[14555.37336],"iteration":590,"passed_time":33.89540002,"remaining_time":23.45722269},
{"learn":[14543.71594],"iteration":591,"passed_time":33.95764291,"remaining_time":23.40324038},
{"learn":[14534.6579],"iteration":592,"passed_time":34.01523716,"remaining_time":23.34603967},
{"learn":[14530.02439],"iteration":593,"passed_time":34.07124476,"remaining_time":23.28775315},
{"learn":[14511.89188],"iteration":594,"passed_time":34.13567859,"remaining_time":23.2352098},
{"learn":[14497.7088],"iteration":595,"passed_time":34.19317178,"remaining_time":23.17792181},
{"learn":[14486.16766],"iteration":596,"passed_time":34.24954684,"remaining_time":23.11987835},
{"learn":[14468.13782],"iteration":597,"passed_time":34.30684997,"remaining_time":23.06246436},
{"learn":[14458.70477],"iteration":598,"passed_time":34.36275115,"remaining_time":23.00411221},
{"learn":[14457.43691],"iteration":599,"passed_time":34.41903713,"remaining_time":22.94602475},
{"learn":[14441.17933],"iteration":600,"passed_time":34.4818631,"remaining_time":22.89228515},
{"learn":[14434.17846],"iteration":601,"passed_time":34.54137756,"remaining_time":22.83632603},
{"learn":[14428.95087],"iteration":602,"passed_time":34.60216878,"remaining_time":22.78119569},
{"learn":[14413.83012],"iteration":603,"passed_time":34.66497029,"remaining_time":22.72736463},
{"learn":[14408.79453],"iteration":604,"passed_time":34.71731261,"remaining_time":22.66667518},
{"learn":[14401.3057],"iteration":605,"passed_time":34.77013516,"remaining_time":22.6063255},
{"learn":[14391.03247],"iteration":606,"passed_time":34.8221842,"remaining_time":22.54549982},
{"learn":[14381.32935],"iteration":607,"passed_time":34.88415621,"remaining_time":22.49110071},
{"learn":[14365.63545],"iteration":608,"passed_time":34.94098401,"remaining_time":22.43337397},
{"learn":[14353.31626],"iteration":609,"passed_time":34.99869861,"remaining_time":22.37621715},
{"learn":[14345.37939],"iteration":610,"passed_time":35.05112853,"remaining_time":22.31569394},
{"learn":[14332.00447],"iteration":611,"passed_time":35.11791503,"remaining_time":22.26429907},
{"learn":[14323.36267],"iteration":612,"passed_time":35.19638287,"remaining_time":22.22022867},
{"learn":[14318.20355],"iteration":613,"passed_time":35.25648921,"remaining_time":22.16450299},
{"learn":[14307.30799],"iteration":614,"passed_time":35.3190278,"remaining_time":22.11028569},
{"learn":[14301.08794],"iteration":615,"passed_time":35.38235219,"remaining_time":22.05653124},
{"learn":[14292.27218],"iteration":616,"passed_time":35.43493416,"remaining_time":21.99607745},
{"learn":[14281.36518],"iteration":617,"passed_time":35.49041795,"remaining_time":21.93744281},
{"learn":[14272.85818],"iteration":618,"passed_time":35.54574,"remaining_time":21.8787188},
{"learn":[14269.8896],"iteration":619,"passed_time":35.60531349,"remaining_time":21.82261149},
{"learn":[14256.37069],"iteration":620,"passed_time":35.66225963,"remaining_time":21.76488953},
{"learn":[14252.07473],"iteration":621,"passed_time":35.71824883,"remaining_time":21.70658851},
{"learn":[14248.82176],"iteration":622,"passed_time":35.77742297,"remaining_time":21.65022225},
{"learn":[14227.34439],"iteration":623,"passed_time":35.83606984,"remaining_time":21.59352926},
{"learn":[14217.3327],"iteration":624,"passed_time":35.89481743,"remaining_time":21.53689046},
{"learn":[14209.117],"iteration":625,"passed_time":35.94997237,"remaining_time":21.47809851},
{"learn":[14198.92022],"iteration":626,"passed_time":36.00901799,"remaining_time":21.42163271},
{"learn":[14195.55223],"iteration":627,"passed_time":36.06816399,"remaining_time":21.36521816},
{"learn":[14178.87759],"iteration":628,"passed_time":36.1244625,"remaining_time":21.3071154},
{"learn":[14170.22194],"iteration":629,"passed_time":36.17671574,"remaining_time":21.24664258},
{"learn":[14161.20806],"iteration":630,"passed_time":36.23257315,"remaining_time":21.18830347},
{"learn":[14145.56181],"iteration":631,"passed_time":36.32274337,"remaining_time":21.14995184},
{"learn":[14126.02915],"iteration":632,"passed_time":36.38084546,"remaining_time":21.09284405},
{"learn":[14119.53864],"iteration":633,"passed_time":36.4419086,"remaining_time":21.0374425},
{"learn":[14112.22463],"iteration":634,"passed_time":36.49928177,"remaining_time":20.97990212},
{"learn":[14105.42917],"iteration":635,"passed_time":36.54952289,"remaining_time":20.9182804},
{"learn":[14097.84786],"iteration":636,"passed_time":36.61037041,"remaining_time":20.86273855},
{"learn":[14076.89146],"iteration":637,"passed_time":36.66272764,"remaining_time":20.8023627},
{"learn":[14072.36153],"iteration":638,"passed_time":36.71703232,"remaining_time":20.74311216},
{"learn":[14068.95137],"iteration":639,"passed_time":36.77719503,"remaining_time":20.68717221},
{"learn":[14052.46024],"iteration":640,"passed_time":36.83058549,"remaining_time":20.62742619},
{"learn":[14043.60128],"iteration":641,"passed_time":36.88699699,"remaining_time":20.56938461},
{"learn":[14025.13911],"iteration":642,"passed_time":36.94427374,"remaining_time":20.5118285},
{"learn":[14011.28178],"iteration":643,"passed_time":36.99927615,"remaining_time":20.45301601},
{"learn":[14000.53832],"iteration":644,"passed_time":37.04915128,"remaining_time":20.39139334},
{"learn":[13991.23798],"iteration":645,"passed_time":37.1115304,"remaining_time":20.33665908},
{"learn":[13985.98232],"iteration":646,"passed_time":37.16935773,"remaining_time":20.27941774},
{"learn":[13974.86158],"iteration":647,"passed_time":37.22481115,"remaining_time":20.22088507},
{"learn":[13953.10905],"iteration":648,"passed_time":37.28069478,"remaining_time":20.16259456},
{"learn":[13940.04213],"iteration":649,"passed_time":37.33459845,"remaining_time":20.10324532},
{"learn":[13929.75011],"iteration":650,"passed_time":37.38773359,"remaining_time":20.04350081},
{"learn":[13919.04937],"iteration":651,"passed_time":37.45056788,"remaining_time":19.98895341},
{"learn":[13912.34775],"iteration":652,"passed_time":37.53130839,"remaining_time":19.94389588},
{"learn":[13902.32422],"iteration":653,"passed_time":37.59984442,"remaining_time":19.89227243},
{"learn":[13885.71813],"iteration":654,"passed_time":37.6744369,"remaining_time":19.84378737},
{"learn":[13873.50908],"iteration":655,"passed_time":37.73040519,"remaining_time":19.78545638},
{"learn":[13870.69761],"iteration":656,"passed_time":37.78420071,"remaining_time":19.72599824},
{"learn":[13863.91627],"iteration":657,"passed_time":37.84179789,"remaining_time":19.66853325},
{"learn":[13849.1025],"iteration":658,"passed_time":37.89255562,"remaining_time":19.60752878},
{"learn":[13840.19221],"iteration":659,"passed_time":37.95376321,"remaining_time":19.55193863},
{"learn":[13834.52036],"iteration":660,"passed_time":38.00804947,"remaining_time":19.4927818},
{"learn":[13827.67217],"iteration":661,"passed_time":38.06802721,"remaining_time":19.43654561},
{"learn":[13814.56507],"iteration":662,"passed_time":38.1262944,"remaining_time":19.37942868},
{"learn":[13812.31453],"iteration":663,"passed_time":38.18496828,"remaining_time":19.32251407},
{"learn":[13807.89708],"iteration":664,"passed_time":38.2378847,"remaining_time":19.26269379},
{"learn":[13802.06271],"iteration":665,"passed_time":38.29859991,"remaining_time":19.20680536},
{"learn":[13788.9935],"iteration":666,"passed_time":38.36134319,"remaining_time":19.15191497},
{"learn":[13774.09062],"iteration":667,"passed_time":38.41729191,"remaining_time":19.09362412},
{"learn":[13759.37892],"iteration":668,"passed_time":38.47108337,"remaining_time":19.03427294},
{"learn":[13746.04264],"iteration":669,"passed_time":38.53110388,"remaining_time":18.97800639},
{"learn":[13741.37639],"iteration":670,"passed_time":38.58764292,"remaining_time":18.92002164},
{"learn":[13732.4014],"iteration":671,"passed_time":38.64076918,"remaining_time":18.86037543},
{"learn":[13707.14985],"iteration":672,"passed_time":38.70456496,"remaining_time":18.80593275},
{"learn":[13702.4572],"iteration":673,"passed_time":38.76068272,"remaining_time":18.74774861},
{"learn":[13696.42043],"iteration":674,"passed_time":38.8204514,"remaining_time":18.69132845},
{"learn":[13683.33366],"iteration":675,"passed_time":38.87543918,"remaining_time":18.63260695},
{"learn":[13681.68454],"iteration":676,"passed_time":38.92993922,"remaining_time":18.57366376},
{"learn":[13672.11531],"iteration":677,"passed_time":38.98717601,"remaining_time":18.51603345},
{"learn":[13654.55406],"iteration":678,"passed_time":39.04884606,"remaining_time":18.46050013},
{"learn":[13630.10299],"iteration":679,"passed_time":39.11137803,"remaining_time":18.40535437},
{"learn":[13624.81484],"iteration":680,"passed_time":39.16915991,"remaining_time":18.34796184},
{"learn":[13612.97094],"iteration":681,"passed_time":39.23210999,"remaining_time":18.29297797},
{"learn":[13606.93124],"iteration":682,"passed_time":39.28379508,"remaining_time":18.23274237},
{"learn":[13601.36432],"iteration":683,"passed_time":39.3395094,"remaining_time":18.17439323},
{"learn":[13596.16413],"iteration":684,"passed_time":39.40074108,"remaining_time":18.11858896},
{"learn":[13591.43059],"iteration":685,"passed_time":39.46110508,"remaining_time":18.06237172},
{"learn":[13580.53268],"iteration":686,"passed_time":39.52014732,"remaining_time":18.00554019},
{"learn":[13576.08965],"iteration":687,"passed_time":39.57757155,"remaining_time":17.94796849},
{"learn":[13573.10975],"iteration":688,"passed_time":39.63332049,"remaining_time":17.88964104},
{"learn":[13562.58997],"iteration":689,"passed_time":39.68930006,"remaining_time":17.83142466},
{"learn":[13550.35269],"iteration":690,"passed_time":39.74289348,"remaining_time":17.77214774},
{"learn":[13541.22209],"iteration":691,"passed_time":39.8047638,"remaining_time":17.71657117},
{"learn":[13531.17946],"iteration":692,"passed_time":39.86228168,"remaining_time":17.65904831},
{"learn":[13522.09597],"iteration":693,"passed_time":39.92268669,"remaining_time":17.60279846},
{"learn":[13520.35624],"iteration":694,"passed_time":39.98208253,"remaining_time":17.54609377},
{"learn":[13504.12919],"iteration":695,"passed_time":40.1042223,"remaining_time":17.51678675},
{"learn":[13502.2154],"iteration":696,"passed_time":40.19373051,"remaining_time":17.47302775},
{"learn":[13491.75961],"iteration":697,"passed_time":40.26187951,"remaining_time":17.41989629},
{"learn":[13487.28563],"iteration":698,"passed_time":40.32507561,"remaining_time":17.36458907},
{"learn":[13486.01866],"iteration":699,"passed_time":40.38660566,"remaining_time":17.30854528},
{"learn":[13478.68402],"iteration":700,"passed_time":40.44911468,"remaining_time":17.25290341},
{"learn":[13472.29149],"iteration":701,"passed_time":40.50732031,"remaining_time":17.19541518},
{"learn":[13459.23446],"iteration":702,"passed_time":40.57046765,"remaining_time":17.14001265},
{"learn":[13454.71574],"iteration":703,"passed_time":40.63072665,"remaining_time":17.08337371},
{"learn":[13453.47939],"iteration":704,"passed_time":40.69555515,"remaining_time":17.02863655},
{"learn":[13438.68913],"iteration":705,"passed_time":40.77114791,"remaining_time":16.97835338},
{"learn":[13433.56299],"iteration":706,"passed_time":40.83451851,"remaining_time":16.92293341},
{"learn":[13414.95884],"iteration":707,"passed_time":40.90183617,"remaining_time":16.86911887},
{"learn":[13397.30723],"iteration":708,"passed_time":40.96335459,"remaining_time":16.81288602},
{"learn":[13391.54178],"iteration":709,"passed_time":41.022599,"remaining_time":16.75570945},
{"learn":[13382.46765],"iteration":710,"passed_time":41.08159517,"remaining_time":16.69842617},
{"learn":[13365.66967],"iteration":711,"passed_time":41.15437171,"remaining_time":16.64671215},
{"learn":[13354.04638],"iteration":712,"passed_time":41.22669184,"remaining_time":16.59475534},
{"learn":[13350.15156],"iteration":713,"passed_time":41.29295235,"remaining_time":16.54031425},
{"learn":[13346.7948],"iteration":714,"passed_time":41.35434464,"remaining_time":16.48389961},
{"learn":[13336.55745],"iteration":715,"passed_time":41.43463629,"remaining_time":16.43496747},
{"learn":[13321.64424],"iteration":716,"passed_time":41.49338715,"remaining_time":16.3774457},
{"learn":[13310.45243],"iteration":717,"passed_time":41.57346725,"remaining_time":16.32829772},
{"learn":[13302.32348],"iteration":718,"passed_time":41.64417099,"remaining_time":16.27539923},
{"learn":[13294.6804],"iteration":719,"passed_time":41.70577531,"remaining_time":16.21891262},
{"learn":[13285.97614],"iteration":720,"passed_time":41.77976736,"remaining_time":16.1672054},
{"learn":[13275.29462],"iteration":721,"passed_time":41.83340664,"remaining_time":16.10759978},
{"learn":[13273.36771],"iteration":722,"passed_time":41.8905608,"remaining_time":16.04935732},
{"learn":[13265.97186],"iteration":723,"passed_time":41.95001643,"remaining_time":15.99199521},
{"learn":[13254.84349],"iteration":724,"passed_time":42.01597218,"remaining_time":15.9370929},
{"learn":[13249.73207],"iteration":725,"passed_time":42.07996213,"remaining_time":15.88141822},
{"learn":[13237.47825],"iteration":726,"passed_time":42.1456438,"remaining_time":15.82635592},
{"learn":[13221.96993],"iteration":727,"passed_time":42.20823128,"remaining_time":15.77010839},
{"learn":[13213.55628],"iteration":728,"passed_time":42.26701279,"remaining_time":15.71242862},
{"learn":[13200.23654],"iteration":729,"passed_time":42.33537133,"remaining_time":15.65828803},
{"learn":[13190.67745],"iteration":730,"passed_time":42.40668591,"remaining_time":15.60519632},
{"learn":[13181.04909],"iteration":731,"passed_time":42.46793222,"remaining_time":15.54836863},
{"learn":[13173.31303],"iteration":732,"passed_time":42.54230966,"remaining_time":15.49631198},
{"learn":[13160.54623],"iteration":733,"passed_time":42.60408186,"remaining_time":15.4396264},
{"learn":[13155.38509],"iteration":734,"passed_time":42.67259554,"remaining_time":15.38535758},
{"learn":[13148.40509],"iteration":735,"passed_time":42.73282787,"remaining_time":15.32807956},
{"learn":[13136.3078],"iteration":736,"passed_time":42.79417615,"remaining_time":15.27119176},
{"learn":[13132.23184],"iteration":737,"passed_time":42.92200213,"remaining_time":15.23789235},
{"learn":[13121.10262],"iteration":738,"passed_time":43.04818134,"remaining_time":15.20375552},
{"learn":[13111.66301],"iteration":739,"passed_time":43.28206957,"remaining_time":15.20721363},
{"learn":[13102.62328],"iteration":740,"passed_time":43.42576938,"remaining_time":15.17850779},
{"learn":[13098.36457],"iteration":741,"passed_time":43.73272676,"remaining_time":15.20625809},
{"learn":[13088.11702],"iteration":742,"passed_time":43.87060437,"remaining_time":15.17462358},
{"learn":[13081.51982],"iteration":743,"passed_time":43.96886041,"remaining_time":15.12907025},
{"learn":[13071.59251],"iteration":744,"passed_time":44.05370148,"remaining_time":15.07878373},
{"learn":[13065.4066],"iteration":745,"passed_time":44.13158971,"remaining_time":15.02603725},
{"learn":[13058.38175],"iteration":746,"passed_time":44.20153506,"remaining_time":14.97053329},
{"learn":[13055.63958],"iteration":747,"passed_time":44.27488985,"remaining_time":14.91613936},
{"learn":[13054.75191],"iteration":748,"passed_time":44.36286341,"remaining_time":14.86659375},
{"learn":[13046.57676],"iteration":749,"passed_time":44.4233834,"remaining_time":14.80779447},
{"learn":[13041.20195],"iteration":750,"passed_time":44.48744604,"remaining_time":14.7501652},
{"learn":[13038.13443],"iteration":751,"passed_time":44.55109584,"remaining_time":14.69238267},
{"learn":[13025.18131],"iteration":752,"passed_time":44.61950896,"remaining_time":14.63614703},
{"learn":[13016.11787],"iteration":753,"passed_time":44.67938003,"remaining_time":14.57709216},
{"learn":[13003.90051],"iteration":754,"passed_time":44.74106638,"remaining_time":14.51862419},
{"learn":[12993.09343],"iteration":755,"passed_time":44.81863993,"remaining_time":14.46527532},
{"learn":[12982.2755],"iteration":756,"passed_time":44.90498347,"remaining_time":14.41467765},
{"learn":[12980.78868],"iteration":757,"passed_time":45.02382123,"remaining_time":14.37435981},
{"learn":[12968.5882],"iteration":758,"passed_time":45.113115,"remaining_time":14.32445417},
{"learn":[12944.48654],"iteration":759,"passed_time":45.19955691,"remaining_time":14.27354429},
{"learn":[12938.39111],"iteration":760,"passed_time":45.33647389,"remaining_time":14.23839324},
{"learn":[12917.67727],"iteration":761,"passed_time":45.41560037,"remaining_time":14.18492505},
{"learn":[12911.15761],"iteration":762,"passed_time":45.5042066,"remaining_time":14.13433416},
{"learn":[12879.55523],"iteration":763,"passed_time":45.59672571,"remaining_time":14.08485244},
{"learn":[12864.05938],"iteration":764,"passed_time":45.66376523,"remaining_time":14.02743115},
{"learn":[12852.52283],"iteration":765,"passed_time":45.74038182,"remaining_time":13.97291037},
{"learn":[12849.18733],"iteration":766,"passed_time":45.80887686,"remaining_time":13.91586481},
{"learn":[12845.90195],"iteration":767,"passed_time":45.88129973,"remaining_time":13.85997596},
{"learn":[12838.53635],"iteration":768,"passed_time":45.94474838,"remaining_time":13.80134834},
{"learn":[12835.15306],"iteration":769,"passed_time":46.0067119,"remaining_time":13.74226459},
{"learn":[12827.85591],"iteration":770,"passed_time":46.06876156,"remaining_time":13.68319896},
{"learn":[12820.72052],"iteration":771,"passed_time":46.13150802,"remaining_time":13.62433139},
{"learn":[12813.72736],"iteration":772,"passed_time":46.19110391,"remaining_time":13.56452857},
{"learn":[12798.57565],"iteration":773,"passed_time":46.25150814,"remaining_time":13.50496232},
{"learn":[12786.58483],"iteration":774,"passed_time":46.32749587,"remaining_time":13.44991816},
{"learn":[12776.13656],"iteration":775,"passed_time":46.40666761,"remaining_time":13.3957391},
{"learn":[12771.10853],"iteration":776,"passed_time":46.4820505,"remaining_time":13.34040832},
{"learn":[12765.98225],"iteration":777,"passed_time":46.55683681,"remaining_time":13.28485575},
{"learn":[12763.5137],"iteration":778,"passed_time":46.62507674,"remaining_time":13.22739661},
{"learn":[12755.41773],"iteration":779,"passed_time":46.69185785,"remaining_time":13.16949837},
{"learn":[12737.18031],"iteration":780,"passed_time":46.76163797,"remaining_time":13.11241833},
{"learn":[12731.42912],"iteration":781,"passed_time":46.82583276,"remaining_time":13.05374877},
{"learn":[12722.93871],"iteration":782,"passed_time":46.88755322,"remaining_time":12.99437937},
{"learn":[12709.16014],"iteration":783,"passed_time":46.95318877,"remaining_time":12.93608262},
{"learn":[12699.25309],"iteration":784,"passed_time":47.02062645,"remaining_time":12.87826075},
{"learn":[12690.841],"iteration":785,"passed_time":47.0782523,"remaining_time":12.81774299},
{"learn":[12686.52374],"iteration":786,"passed_time":47.14538089,"remaining_time":12.75980448},
{"learn":[12681.85362],"iteration":787,"passed_time":47.20492417,"remaining_time":12.69980193},
{"learn":[12677.11173],"iteration":788,"passed_time":47.27196175,"remaining_time":12.64180473},
{"learn":[12674.60069],"iteration":789,"passed_time":47.33687705,"remaining_time":12.58322048},
{"learn":[12670.42662],"iteration":790,"passed_time":47.40030037,"remaining_time":12.52422601},
{"learn":[12660.65753],"iteration":791,"passed_time":47.46751761,"remaining_time":12.46621675},
{"learn":[12650.64604],"iteration":792,"passed_time":47.5442473,"remaining_time":12.41066733},
{"learn":[12643.12745],"iteration":793,"passed_time":47.614238,"remaining_time":12.35331616},
{"learn":[12635.09803],"iteration":794,"passed_time":47.67749301,"remaining_time":12.29419631},
{"learn":[12629.01563],"iteration":795,"passed_time":47.74505296,"remaining_time":12.23616935},
{"learn":[12620.26608],"iteration":796,"passed_time":47.81160374,"remaining_time":12.17786143},
{"learn":[12615.76587],"iteration":797,"passed_time":47.87799319,"remaining_time":12.11949201},
{"learn":[12611.84944],"iteration":798,"passed_time":47.94575736,"remaining_time":12.06144835},
{"learn":[12607.03045],"iteration":799,"passed_time":48.00541515,"remaining_time":12.00135379},
{"learn":[12605.417],"iteration":800,"passed_time":48.07291386,"remaining_time":11.94320831},
{"learn":[12592.78849],"iteration":801,"passed_time":48.13459467,"remaining_time":11.88360317},
{"learn":[12581.97824],"iteration":802,"passed_time":48.19859771,"remaining_time":11.82456258},
{"learn":[12576.01407],"iteration":803,"passed_time":48.26617823,"remaining_time":11.76638176},
{"learn":[12574.78854],"iteration":804,"passed_time":48.34176345,"remaining_time":11.71011661},
{"learn":[12573.8696],"iteration":805,"passed_time":48.40530041,"remaining_time":11.65090357},
{"learn":[12560.07505],"iteration":806,"passed_time":48.47228423,"remaining_time":11.59250416},
{"learn":[12553.95389],"iteration":807,"passed_time":48.53871672,"remaining_time":11.53395249},
{"learn":[12545.77566],"iteration":808,"passed_time":48.61144403,"remaining_time":11.4768675},
{"learn":[12541.60859],"iteration":809,"passed_time":48.68230511,"remaining_time":11.41930614},
{"learn":[12534.63008],"iteration":810,"passed_time":48.75439965,"remaining_time":11.36199942},
{"learn":[12529.82005],"iteration":811,"passed_time":48.81471584,"remaining_time":11.30192928},
{"learn":[12523.95879],"iteration":812,"passed_time":48.8868008,"remaining_time":11.2445655},
{"learn":[12509.19481],"iteration":813,"passed_time":48.95282329,"remaining_time":11.18578026},
{"learn":[12496.89782],"iteration":814,"passed_time":49.01919356,"remaining_time":11.12705621},
{"learn":[12491.87862],"iteration":815,"passed_time":49.08087776,"remaining_time":11.06725675},
{"learn":[12483.59968],"iteration":816,"passed_time":49.14335056,"remaining_time":11.00762932},
{"learn":[12476.61573],"iteration":817,"passed_time":49.20562235,"remaining_time":10.9479502},
{"learn":[12472.33603],"iteration":818,"passed_time":49.2593041,"remaining_time":10.88636635},
{"learn":[12468.34462],"iteration":819,"passed_time":49.33578576,"remaining_time":10.82980663},
{"learn":[12455.18668],"iteration":820,"passed_time":49.42291849,"remaining_time":10.7755206},
{"learn":[12446.60071],"iteration":821,"passed_time":49.49345047,"remaining_time":10.71755983},
{"learn":[12442.66305],"iteration":822,"passed_time":49.55929905,"remaining_time":10.65856128},
{"learn":[12433.03782],"iteration":823,"passed_time":49.62580409,"remaining_time":10.59968631},
{"learn":[12424.62125],"iteration":824,"passed_time":49.74446963,"remaining_time":10.55185719},
{"learn":[12418.6461],"iteration":825,"passed_time":49.81306416,"remaining_time":10.49330892},
{"learn":[12410.96711],"iteration":826,"passed_time":49.88625739,"remaining_time":10.43569834},
{"learn":[12405.65971],"iteration":827,"passed_time":49.95637272,"remaining_time":10.37741076},
{"learn":[12386.71465],"iteration":828,"passed_time":50.02143084,"remaining_time":10.31805148},
{"learn":[12382.22903],"iteration":829,"passed_time":50.07948937,"remaining_time":10.25724481},
{"learn":[12375.06462],"iteration":830,"passed_time":50.1449496,"remaining_time":10.19795004},
{"learn":[12357.23504],"iteration":831,"passed_time":50.20553445,"remaining_time":10.137656},
{"learn":[12342.98159],"iteration":832,"passed_time":50.26876455,"remaining_time":10.07789157},
{"learn":[12334.16618],"iteration":833,"passed_time":50.33798023,"remaining_time":10.01931021},
{"learn":[12318.25477],"iteration":834,"passed_time":50.42801278,"remaining_time":9.964816897},
{"learn":[12307.16276],"iteration":835,"passed_time":50.49773945,"remaining_time":9.906255108},
{"learn":[12299.64829],"iteration":836,"passed_time":50.56093825,"remaining_time":9.846395383},
{"learn":[12295.96349],"iteration":837,"passed_time":50.62597059,"remaining_time":9.786882142},
{"learn":[12277.60549],"iteration":838,"passed_time":50.69690976,"remaining_time":9.72848924},
{"learn":[12269.64737],"iteration":839,"passed_time":50.76565595,"remaining_time":9.669648753},
{"learn":[12260.39431],"iteration":840,"passed_time":50.82905677,"remaining_time":9.60977411},
{"learn":[12258.09313],"iteration":841,"passed_time":50.89708164,"remaining_time":9.550758788},
{"learn":[12256.75325],"iteration":842,"passed_time":50.96630686,"remaining_time":9.491945643},
{"learn":[12246.90239],"iteration":843,"passed_time":51.02984085,"remaining_time":9.432055892},
{"learn":[12240.59751],"iteration":844,"passed_time":51.09059136,"remaining_time":9.371646936},
{"learn":[12229.05646],"iteration":845,"passed_time":51.15424466,"remaining_time":9.311765576},
{"learn":[12215.92417],"iteration":846,"passed_time":51.26540491,"remaining_time":9.26045685},
{"learn":[12209.36317],"iteration":847,"passed_time":51.33505141,"remaining_time":9.201565818},
{"learn":[12200.7743],"iteration":848,"passed_time":51.39707152,"remaining_time":9.141293051},
{"learn":[12196.23803],"iteration":849,"passed_time":51.46176415,"remaining_time":9.08148779},
{"learn":[12186.27007],"iteration":850,"passed_time":51.53158392,"remaining_time":9.022568748},
{"learn":[12179.36003],"iteration":851,"passed_time":51.5973094,"remaining_time":8.962912901},
{"learn":[12172.32238],"iteration":852,"passed_time":51.67772368,"remaining_time":8.905774186},
{"learn":[12156.84629],"iteration":853,"passed_time":51.73826035,"remaining_time":8.845182684},
{"learn":[12147.62071],"iteration":854,"passed_time":51.79901218,"remaining_time":8.784627796},
{"learn":[12143.14429],"iteration":855,"passed_time":51.85322814,"remaining_time":8.722972958},
{"learn":[12138.76409],"iteration":856,"passed_time":51.91311455,"remaining_time":8.662281657},
{"learn":[12128.21485],"iteration":857,"passed_time":51.97117304,"remaining_time":8.601289711},
{"learn":[12125.35491],"iteration":858,"passed_time":52.03795107,"remaining_time":8.541735857},
{"learn":[12119.14093],"iteration":859,"passed_time":52.09928678,"remaining_time":8.481279243},
{"learn":[12107.92919],"iteration":860,"passed_time":52.15936942,"remaining_time":8.420618292},
{"learn":[12103.46203],"iteration":861,"passed_time":52.22273773,"remaining_time":8.360484695},
{"learn":[12096.2153],"iteration":862,"passed_time":52.2889198,"remaining_time":8.300790281},
{"learn":[12092.60012],"iteration":863,"passed_time":52.34773522,"remaining_time":8.239921285},
{"learn":[12082.78895],"iteration":864,"passed_time":52.41451922,"remaining_time":8.180300687},
{"learn":[12074.52706],"iteration":865,"passed_time":52.47292241,"remaining_time":8.119366747},
{"learn":[12069.90064],"iteration":866,"passed_time":52.53221903,"remaining_time":8.058575699},
{"learn":[12061.24256],"iteration":867,"passed_time":52.59232152,"remaining_time":7.997910645},
{"learn":[12058.34608],"iteration":868,"passed_time":52.64286973,"remaining_time":7.935806598},
{"learn":[12047.80281],"iteration":869,"passed_time":52.69963515,"remaining_time":7.874658126},
{"learn":[12043.97026],"iteration":870,"passed_time":52.75611203,"remaining_time":7.813476983},
{"learn":[12035.06752],"iteration":871,"passed_time":52.81297705,"remaining_time":7.752363604},
{"learn":[12029.80457],"iteration":872,"passed_time":52.86482888,"remaining_time":7.690530661},
{"learn":[12017.67637],"iteration":873,"passed_time":52.92159545,"remaining_time":7.629429092},
{"learn":[12010.41644],"iteration":874,"passed_time":52.98491701,"remaining_time":7.569273859},
{"learn":[12003.0814],"iteration":875,"passed_time":53.03459569,"remaining_time":7.507180212},
{"learn":[11997.52912],"iteration":876,"passed_time":53.09212026,"remaining_time":7.446215271},
{"learn":[11993.96734],"iteration":877,"passed_time":53.14303688,"remaining_time":7.384339977},
{"learn":[11981.42123],"iteration":878,"passed_time":53.19549764,"remaining_time":7.322702178},
{"learn":[11969.65621],"iteration":879,"passed_time":53.25352215,"remaining_time":7.261843929},
{"learn":[11963.35471],"iteration":880,"passed_time":53.31709151,"remaining_time":7.201741077},
{"learn":[11942.18672],"iteration":881,"passed_time":53.36835114,"remaining_time":7.139983486},
{"learn":[11938.95954],"iteration":882,"passed_time":53.42171244,"remaining_time":7.078528149},
{"learn":[11931.17559],"iteration":883,"passed_time":53.47716479,"remaining_time":7.017365516},
{"learn":[11920.84819],"iteration":884,"passed_time":53.5440569,"remaining_time":6.957702309},
{"learn":[11912.79214],"iteration":885,"passed_time":53.60446092,"remaining_time":6.897187974},
{"learn":[11907.67206],"iteration":886,"passed_time":53.65834285,"remaining_time":6.835843002},
{"learn":[11900.36412],"iteration":887,"passed_time":53.71444584,"remaining_time":6.774794971},
{"learn":[11893.78407],"iteration":888,"passed_time":53.77091989,"remaining_time":6.713804395},
{"learn":[11876.62762],"iteration":889,"passed_time":53.82364116,"remaining_time":6.652360143},
{"learn":[11858.4188],"iteration":890,"passed_time":53.87669272,"remaining_time":6.590975878},
{"learn":[11855.88713],"iteration":891,"passed_time":53.92773347,"remaining_time":6.529366833},
{"learn":[11852.07161],"iteration":892,"passed_time":53.97777083,"remaining_time":6.467661231},
{"learn":[11846.71721],"iteration":893,"passed_time":54.03043509,"remaining_time":6.406293199},
{"learn":[11834.82374],"iteration":894,"passed_time":54.0865649,"remaining_time":6.34535119},
{"learn":[11825.95421],"iteration":895,"passed_time":54.13892439,"remaining_time":6.283982295},
{"learn":[11815.97584],"iteration":896,"passed_time":54.19055577,"remaining_time":6.222549883},
{"learn":[11812.29091],"iteration":897,"passed_time":54.26955263,"remaining_time":6.164247626},
{"learn":[11792.97685],"iteration":898,"passed_time":54.33281349,"remaining_time":6.104131438},
{"learn":[11783.55473],"iteration":899,"passed_time":54.38810801,"remaining_time":6.043123112},
{"learn":[11774.8363],"iteration":900,"passed_time":54.44356404,"remaining_time":5.982145217},
{"learn":[11765.6933],"iteration":901,"passed_time":54.50399872,"remaining_time":5.921720482},
{"learn":[11761.44678],"iteration":902,"passed_time":54.56628112,"remaining_time":5.861494207},
{"learn":[11752.07006],"iteration":903,"passed_time":54.62256351,"remaining_time":5.800626213},
{"learn":[11740.37075],"iteration":904,"passed_time":54.67685367,"remaining_time":5.739559225},
{"learn":[11738.93502],"iteration":905,"passed_time":54.7394057,"remaining_time":5.679364389},
{"learn":[11721.87475],"iteration":906,"passed_time":54.79712381,"remaining_time":5.618668704},
{"learn":[11704.74797],"iteration":907,"passed_time":54.85165373,"remaining_time":5.557656545},
{"learn":[11699.33841],"iteration":908,"passed_time":54.90454617,"remaining_time":5.496494721},
{"learn":[11695.92343],"iteration":909,"passed_time":54.96844337,"remaining_time":5.436439455},
{"learn":[11686.95791],"iteration":910,"passed_time":55.02663062,"remaining_time":5.37581792},
{"learn":[11681.82334],"iteration":911,"passed_time":55.08221731,"remaining_time":5.314950793},
{"learn":[11673.42859],"iteration":912,"passed_time":55.13923077,"remaining_time":5.25423119},
{"learn":[11666.4163],"iteration":913,"passed_time":55.19427677,"remaining_time":5.193334576},
{"learn":[11656.77687],"iteration":914,"passed_time":55.25264079,"remaining_time":5.132758981},
{"learn":[11646.35334],"iteration":915,"passed_time":55.31271009,"remaining_time":5.072344594},
{"learn":[11640.16616],"iteration":916,"passed_time":55.37016069,"remaining_time":5.011693934},
{"learn":[11637.18263],"iteration":917,"passed_time":55.42978519,"remaining_time":4.951244428},
{"learn":[11624.93305],"iteration":918,"passed_time":55.48693598,"remaining_time":4.890578688},
{"learn":[11610.89785],"iteration":919,"passed_time":55.54169436,"remaining_time":4.829712553},
{"learn":[11607.51498],"iteration":920,"passed_time":55.59794155,"remaining_time":4.768987386},
{"learn":[11605.71226],"iteration":921,"passed_time":55.65684401,"remaining_time":4.708496565},
{"learn":[11595.16599],"iteration":922,"passed_time":55.71864423,"remaining_time":4.648250927},
{"learn":[11589.77495],"iteration":923,"passed_time":55.77538894,"remaining_time":4.587586103},
{"learn":[11579.22136],"iteration":924,"passed_time":55.83957258,"remaining_time":4.527532912},
{"learn":[11570.04125],"iteration":925,"passed_time":55.89838262,"remaining_time":4.467041376},
{"learn":[11558.14891],"iteration":926,"passed_time":55.95532037,"remaining_time":4.406406027},
{"learn":[11553.15589],"iteration":927,"passed_time":56.01307928,"remaining_time":4.345842358},
{"learn":[11546.95676],"iteration":928,"passed_time":56.06963045,"remaining_time":4.285192424},
{"learn":[11540.43935],"iteration":929,"passed_time":56.12635447,"remaining_time":4.224564315},
{"learn":[11539.4705],"iteration":930,"passed_time":56.19050957,"remaining_time":4.164495339},
{"learn":[11526.17562],"iteration":931,"passed_time":56.24563177,"remaining_time":4.103758541},
{"learn":[11518.50114],"iteration":932,"passed_time":56.29848502,"remaining_time":4.042870843},
{"learn":[11509.45111],"iteration":933,"passed_time":56.36134692,"remaining_time":3.982707598},
{"learn":[11496.8952],"iteration":934,"passed_time":56.41955054,"remaining_time":3.922214744},
{"learn":[11492.01049],"iteration":935,"passed_time":56.47793142,"remaining_time":3.8617389},
{"learn":[11479.74149],"iteration":936,"passed_time":56.53432693,"remaining_time":3.801134041},
{"learn":[11468.75332],"iteration":937,"passed_time":56.59517524,"remaining_time":3.740832478},
{"learn":[11462.48851],"iteration":938,"passed_time":56.65021882,"remaining_time":3.680152661},
{"learn":[11456.56741],"iteration":939,"passed_time":56.71239283,"remaining_time":3.619939968},
{"learn":[11444.06847],"iteration":940,"passed_time":56.76526957,"remaining_time":3.559140175},
{"learn":[11438.93963],"iteration":941,"passed_time":56.82243182,"remaining_time":3.498621068},
{"learn":[11436.74743],"iteration":942,"passed_time":56.88481754,"remaining_time":3.438424814},
{"learn":[11432.59134],"iteration":943,"passed_time":56.93980646,"remaining_time":3.377785129},
{"learn":[11428.8757],"iteration":944,"passed_time":56.9972596,"remaining_time":3.317300823},
{"learn":[11421.57671],"iteration":945,"passed_time":57.05624837,"remaining_time":3.256910583},
{"learn":[11418.43648],"iteration":946,"passed_time":57.11291756,"remaining_time":3.196393485},
{"learn":[11413.97946],"iteration":947,"passed_time":57.16493986,"remaining_time":3.135629612},
{"learn":[11403.56302],"iteration":948,"passed_time":57.2352635,"remaining_time":3.075867691},
{"learn":[11393.25173],"iteration":949,"passed_time":57.28929695,"remaining_time":3.015226155},
{"learn":[11386.86521],"iteration":950,"passed_time":57.34772351,"remaining_time":2.954824871},
{"learn":[11378.76612],"iteration":951,"passed_time":57.40125974,"remaining_time":2.894181163},
{"learn":[11372.20422],"iteration":952,"passed_time":57.45615358,"remaining_time":2.833619327},
{"learn":[11369.03471],"iteration":953,"passed_time":57.54597451,"remaining_time":2.774753488},
{"learn":[11363.79654],"iteration":954,"passed_time":57.61961963,"remaining_time":2.715060611},
{"learn":[11356.62039],"iteration":955,"passed_time":57.67565071,"remaining_time":2.654527857},
{"learn":[11339.64139],"iteration":956,"passed_time":57.73416177,"remaining_time":2.594115942},
{"learn":[11323.20882],"iteration":957,"passed_time":57.79152777,"remaining_time":2.533657794},
{"learn":[11308.9762],"iteration":958,"passed_time":57.84877431,"remaining_time":2.473200987},
{"learn":[11301.10559],"iteration":959,"passed_time":57.9072165,"remaining_time":2.412800688},
{"learn":[11297.38557],"iteration":960,"passed_time":57.96679682,"remaining_time":2.352450652},
{"learn":[11284.66115],"iteration":961,"passed_time":58.03084049,"remaining_time":2.292278522},
{"learn":[11270.95047],"iteration":962,"passed_time":58.09422998,"remaining_time":2.232073218},
{"learn":[11264.56832],"iteration":963,"passed_time":58.164557,"remaining_time":2.172120386},
{"learn":[11256.06455],"iteration":964,"passed_time":58.22317843,"remaining_time":2.111721497},
{"learn":[11238.51419],"iteration":965,"passed_time":58.28347444,"remaining_time":2.051385229},
{"learn":[11229.31699],"iteration":966,"passed_time":58.34085194,"remaining_time":1.990949446},
{"learn":[11217.65991],"iteration":967,"passed_time":58.3966928,"remaining_time":1.930469183},
{"learn":[11211.45799],"iteration":968,"passed_time":58.45056278,"remaining_time":1.869935445},
{"learn":[11203.95495],"iteration":969,"passed_time":58.51305257,"remaining_time":1.809682038},
{"learn":[11198.43235],"iteration":970,"passed_time":58.63233367,"remaining_time":1.751120161},
{"learn":[11195.76247],"iteration":971,"passed_time":58.6943511,"remaining_time":1.690783776},
{"learn":[11184.03326],"iteration":972,"passed_time":58.75219265,"remaining_time":1.630328059},
{"learn":[11168.72217],"iteration":973,"passed_time":58.80707131,"remaining_time":1.569798618},
{"learn":[11163.02136],"iteration":974,"passed_time":58.85894432,"remaining_time":1.5092037},
{"learn":[11159.07887],"iteration":975,"passed_time":58.92011882,"remaining_time":1.448855381},
{"learn":[11151.00837],"iteration":976,"passed_time":58.97761011,"remaining_time":1.388418662},
{"learn":[11136.99311],"iteration":977,"passed_time":59.03474374,"remaining_time":1.327979921},
{"learn":[11128.0489],"iteration":978,"passed_time":59.09086711,"remaining_time":1.267526261},
{"learn":[11120.18782],"iteration":979,"passed_time":59.14947066,"remaining_time":1.207132054},
{"learn":[11116.60275],"iteration":980,"passed_time":59.20446257,"remaining_time":1.146671548},
{"learn":[11109.99851],"iteration":981,"passed_time":59.26180256,"remaining_time":1.08626522},
{"learn":[11103.17465],"iteration":982,"passed_time":59.32012155,"remaining_time":1.025882061},
{"learn":[11092.83706],"iteration":983,"passed_time":59.37670426,"remaining_time":0.965474866},
{"learn":[11084.65506],"iteration":984,"passed_time":59.43978823,"remaining_time":0.9051744401},
{"learn":[11078.26918],"iteration":985,"passed_time":59.4948541,"remaining_time":0.8447545206},
{"learn":[11070.30692],"iteration":986,"passed_time":59.54907858,"remaining_time":0.7843343683},
{"learn":[11067.10603],"iteration":987,"passed_time":59.60745681,"remaining_time":0.7239772082},
{"learn":[11065.34619],"iteration":988,"passed_time":59.66812299,"remaining_time":0.6636494974},
{"learn":[11056.1137],"iteration":989,"passed_time":59.72832875,"remaining_time":0.603316452},
{"learn":[11049.61807],"iteration":990,"passed_time":59.7832802,"remaining_time":0.5429359453},
{"learn":[11043.46122],"iteration":991,"passed_time":59.84156727,"remaining_time":0.4825932844},
{"learn":[11036.6974],"iteration":992,"passed_time":59.90016215,"remaining_time":0.4222569336},
{"learn":[11028.89956],"iteration":993,"passed_time":59.95507684,"remaining_time":0.3619018722},
{"learn":[11026.1932],"iteration":994,"passed_time":60.01225575,"remaining_time":0.3015691243},
{"learn":[11019.76486],"iteration":995,"passed_time":60.06879299,"remaining_time":0.2412401325},
{"learn":[11010.72263],"iteration":996,"passed_time":60.12568376,"remaining_time":0.1809198107},
{"learn":[10996.35321],"iteration":997,"passed_time":60.18659111,"remaining_time":0.120614411},
{"learn":[10992.17228],"iteration":998,"passed_time":60.24356738,"remaining_time":0.06030387125},
{"learn":[10985.53397],"iteration":999,"passed_time":60.30258664,"remaining_time":0}
]}